{
  "id": "ggpuqlfu-qd10-f7gs-16a5-ymglngkq9gj2",
  "parameters": {
    "crossoverRate": 0.30000001192092896,
    "eliteSize": 2,
    "tournamentSize": 3,
    "mutationRate": 0.8999999761581421,
    "populationSize": 20
  },
  "populations": [{
    "generation": 0,
    "id": "7ho2hxh3-80ah-334i-dlpb-7bjxwegc8ft1",
    "individuals": [
      {
        "fitness": 0,
        "expressions": {
          "r": "noise(sin(y),sin(noise(mod(tan(sin(max(max((externalVal/externalVal),(x/y)),mod(x,pow(externalVal,externalVal))))),pow((tan(tan(0.834285))/sin(sin((y/y)))),externalVal)),sin(mod((y/x),pow(cos((max(x,externalVal)/(0.23605084/0.78752923))),x))))))",
          "b": "noise(sin(externalVal),sin(noise(mod(tan(sin(max(max((x/externalVal),(y/y)),mod(y,pow(0.75817347,0.628284))))),pow((tan(tan(externalVal))/sin(sin((x/x)))),x)),sin(mod((y/externalVal),pow(cos((max(y,externalVal)/(0.1227994/externalVal))),y))))))",
          "g": "noise(sin(x),sin(noise(mod(tan(sin(max(max((y/x),(y/y)),mod(externalVal,pow(externalVal,externalVal))))),pow((tan(tan(x))/sin(sin((externalVal/0.34548235)))),y)),sin(mod((x/y),pow(cos((max(0.11703181,externalVal)/(y/x))),externalVal))))))"
        }
      },
      {
        "fitness": 0,
        "expressions": {
          "r": "sin(mod(cos(sin(mod((mod(cos(tan(y)),y)/cos(y)),x))),min(pow(tan(x),y),min(0.7929497,(noise(min(max(x,x),mod(noise(externalVal,y),mod(y,0.25944877))),0.6728623)/x)))))",
          "b": "sin(mod(cos(sin(mod((mod(cos(tan(y)),x)/cos(0.09420633)),y))),min(pow(tan(externalVal),y),min(0.2891004,(noise(min(max(x,y),mod(noise(y,externalVal),mod(x,y))),0.19914842)/x)))))",
          "g": "sin(mod(cos(sin(mod((mod(cos(tan(externalVal)),0.18151855)/cos(0.061155558)),x))),min(pow(tan(y),externalVal),min(x,(noise(min(max(0.33601093,0.87114143),mod(noise(x,externalVal),mod(externalVal,0.025215626))),externalVal)/externalVal)))))"
        }
      },
      {
        "fitness": 0,
        "expressions": {
          "r": "0.48974824",
          "b": "0.10826135",
          "g": "y"
        }
      },
      {
        "fitness": 0,
        "expressions": {
          "r": "tan(noise(tan(y),y))",
          "b": "tan(noise(tan(0.3923664),externalVal))",
          "g": "tan(noise(tan(externalVal),x))"
        }
      },
      {
        "fitness": 0,
        "expressions": {
          "r": "pow(pow(sin(x),max(externalVal,sin(cos(min(x,(((externalVal/0.6695981)/x)/y)))))),y)",
          "b": "pow(pow(sin(x),max(externalVal,sin(cos(min(x,(((y/externalVal)/y)/externalVal)))))),y)",
          "g": "pow(pow(sin(0.79649544),max(y,sin(cos(min(x,(((0.30906677/externalVal)/externalVal)/0.6042032)))))),externalVal)"
        }
      },
      {
        "fitness": 0,
        "expressions": {
          "r": "cos(sin(max(cos(pow(sin(0.11117387),0.7861445)),x)))",
          "b": "cos(sin(max(cos(pow(sin(externalVal),0.6164694)),0.04419303)))",
          "g": "cos(sin(max(cos(pow(sin(externalVal),x)),externalVal)))"
        }
      },
      {
        "fitness": 0,
        "expressions": {
          "r": "mod(externalVal,y)",
          "b": "mod(x,0.34479237)",
          "g": "mod(0.13346004,externalVal)"
        }
      },
      {
        "fitness": 0,
        "expressions": {
          "r": "pow(y,mod(externalVal,cos(noise(pow(min((x/(0.045084476/x)),mod((y/y),sin(min(0.2687211,y)))),noise(cos(mod(pow(x,y),0.3841071)),sin(tan(pow(x,x))))),sin(tan(externalVal))))))",
          "b": "pow(y,mod(0.66068316,cos(noise(pow(min((y/(0.29678178/0.6053262)),mod((y/externalVal),sin(min(y,0.40767813)))),noise(cos(mod(pow(y,x),0.18697834)),sin(tan(pow(x,0.971123))))),sin(tan(0.0608418))))))",
          "g": "pow(0.25185847,mod(externalVal,cos(noise(pow(min((y/(externalVal/x)),mod((y/0.8406465),sin(min(x,x)))),noise(cos(mod(pow(0.87708116,y),0.36051035)),sin(tan(pow(0.045960188,externalVal))))),sin(tan(x))))))"
        }
      },
      {
        "fitness": 0,
        "expressions": {
          "r": "mod(cos(noise(noise(externalVal,x),y)),y)",
          "b": "mod(cos(noise(noise(y,0.9426367),x)),externalVal)",
          "g": "mod(cos(noise(noise(externalVal,externalVal),y)),y)"
        }
      },
      {
        "fitness": 0,
        "expressions": {
          "r": "(tan(max(cos(sin(cos(noise(min(sin(externalVal),sin(x)),tan(min(0.8674822,x)))))),noise(noise(cos(pow(max(noise(y,x),sin(0.913265)),0.21021652)),y),min(sin(cos(sin(mod(x,x)))),sin(0.35470748)))))/pow(cos(max((tan(externalVal)/0.50759387),y)),x))",
          "b": "(tan(max(cos(sin(cos(noise(min(sin(y),sin(x)),tan(min(y,x)))))),noise(noise(cos(pow(max(noise(0.083179235,x),sin(x)),x)),y),min(sin(cos(sin(mod(externalVal,externalVal)))),sin(externalVal)))))/pow(cos(max((tan(externalVal)/y),y)),0.86718345))",
          "g": "(tan(max(cos(sin(cos(noise(min(sin(x),sin(0.68457866)),tan(min(x,externalVal)))))),noise(noise(cos(pow(max(noise(externalVal,x),sin(0.43326497)),0.9275539)),y),min(sin(cos(sin(mod(externalVal,x)))),sin(y)))))/pow(cos(max((tan(y)/y),0.35717297)),0.40935946))"
        }
      },
      {
        "fitness": 0,
        "expressions": {
          "r": "max(pow(sin(min(noise(0.86498785,cos(externalVal)),max((pow(pow(cos(externalVal),tan(x)),max(sin(externalVal),x))/0.5087385),0.8786645))),noise(externalVal,noise(y,sin(y)))),externalVal)",
          "b": "max(pow(sin(min(noise(x,cos(x)),max((pow(pow(cos(externalVal),tan(externalVal)),max(sin(x),y))/externalVal),externalVal))),noise(y,noise(y,sin(externalVal)))),externalVal)",
          "g": "max(pow(sin(min(noise(externalVal,cos(externalVal)),max((pow(pow(cos(y),tan(y)),max(sin(externalVal),0.85567904))/x),0.61984277))),noise(externalVal,noise(externalVal,sin(x)))),x)"
        }
      },
      {
        "fitness": 0,
        "expressions": {
          "r": "pow(noise(cos(pow(mod(noise(sin(min(y,max(x,y))),x),0.23820996),externalVal)),max(noise(sin(max(0.34526277,externalVal)),noise(externalVal,sin(noise(max(sin(0.9934027),x),x)))),0.85670567)),mod(max(externalVal,min(externalVal,pow(max(max((min(x,y)/y),pow(0.8271165,externalVal)),y),min(y,min(sin(max(externalVal,x)),(externalVal/cos(x))))))),tan(mod(max(cos(y),y),x))))",
          "b": "pow(noise(cos(pow(mod(noise(sin(min(y,max(externalVal,externalVal))),0.05538273),0.22770023),0.016528845)),max(noise(sin(max(x,0.63125134)),noise(x,sin(noise(max(sin(y),externalVal),y)))),0.86096644)),mod(max(y,min(x,pow(max(max((min(externalVal,x)/0.26403046),pow(0.9176297,x)),externalVal),min(externalVal,min(sin(max(0.7637005,0.08603215)),(x/cos(0.86053944))))))),tan(mod(max(cos(externalVal),y),0.69569063))))",
          "g": "pow(noise(cos(pow(mod(noise(sin(min(externalVal,max(x,0.27479863))),x),x),0.18375683)),max(noise(sin(max(0.032548904,0.37973928)),noise(externalVal,sin(noise(max(sin(y),0.6517029),0.45545125)))),x)),mod(max(x,min(externalVal,pow(max(max((min(0.38586593,y)/x),pow(0.17360997,externalVal)),x),min(y,min(sin(max(0.33954167,x)),(y/cos(externalVal))))))),tan(mod(max(cos(y),x),y))))"
        }
      },
      {
        "fitness": 0,
        "expressions": {
          "r": "sin(tan(min(y,externalVal)))",
          "b": "sin(tan(min(0.5816355,x)))",
          "g": "sin(tan(min(x,x)))"
        }
      },
      {
        "fitness": 0,
        "expressions": {
          "r": "pow((max(y,mod(cos(0.31801414),y))/max(mod(max(tan(cos(externalVal)),0.22867489),sin(externalVal)),x)),sin(externalVal))",
          "b": "pow((max(y,mod(cos(0.0099236965),y))/max(mod(max(tan(cos(x)),y),sin(y)),y)),sin(y))",
          "g": "pow((max(externalVal,mod(cos(y),y))/max(mod(max(tan(cos(externalVal)),y),sin(externalVal)),externalVal)),sin(y))"
        }
      },
      {
        "fitness": 0,
        "expressions": {
          "r": "externalVal",
          "b": "y",
          "g": "x"
        }
      },
      {
        "fitness": 0,
        "expressions": {
          "r": "sin(pow(cos(x),x))",
          "b": "sin(pow(cos(y),x))",
          "g": "sin(pow(cos(y),externalVal))"
        }
      },
      {
        "fitness": 0,
        "expressions": {
          "r": "0.6361027",
          "b": "y",
          "g": "y"
        }
      },
      {
        "fitness": 0,
        "expressions": {
          "r": "externalVal",
          "b": "x",
          "g": "externalVal"
        }
      },
      {
        "fitness": 0,
        "expressions": {
          "r": "pow(sin(externalVal),max((0.16462278/0.87549615),min(mod(pow(min(externalVal,x),0.18513441),y),pow(cos(tan(noise(x,noise(max(externalVal,x),tan(externalVal))))),y))))",
          "b": "pow(sin(x),max((y/externalVal),min(mod(pow(min(x,0.06114626),0.40623927),x),pow(cos(tan(noise(y,noise(max(0.15686274,0.78261685),tan(0.59931636))))),y))))",
          "g": "pow(sin(externalVal),max((externalVal/externalVal),min(mod(pow(min(0.19219065,externalVal),x),externalVal),pow(cos(tan(noise(0.7687962,noise(max(y,x),tan(0.030393124))))),0.25450516))))"
        }
      },
      {
        "fitness": 0,
        "expressions": {
          "r": "tan(0.6030698)",
          "b": "tan(y)",
          "g": "tan(x)"
        }
      }
    ],
    "timestamp": "21h:19m:27s"
  }],
  "timestamp": "2024-04-16-21-19-26"
}