{
  "id": "ryejlbvx-spux-w13q-z1cm-tlxqt2nym34l",
  "parameters": {
    "crossoverRate": 0.30000001192092896,
    "eliteSize": 2,
    "tournamentSize": 3,
    "mutationRate": 0.8999999761581421,
    "populationSize": 10
  },
  "populations": [{
    "generation": 0,
    "id": "gc1s9ywh-ux4u-xgfh-745v-rfd5w5d8gxzc",
    "individuals": [
      {
        "fitness": 0,
        "expressions": {
          "r": "x",
          "b": "x",
          "g": "0.20632446"
        }
      },
      {
        "fitness": 0,
        "expressions": {
          "r": "(y*var((y/y)))",
          "b": "(x*var((0.49300218/x)))",
          "g": "(0.839312*var((0.74323565/0.048324823)))"
        }
      },
      {
        "fitness": 0,
        "expressions": {
          "r": "y",
          "b": "x",
          "g": "x"
        }
      },
      {
        "fitness": 0,
        "expressions": {
          "r": "pow(tan(sin(x)),0.34984785)",
          "b": "pow(tan(sin(y)),x)",
          "g": "pow(tan(sin(x)),y)"
        }
      },
      {
        "fitness": 0,
        "expressions": {
          "r": "(min(((tan(cos(min(x,x)))-x)*cos(x)),(y/x))-0.7346429)",
          "b": "(min(((tan(cos(min(x,x)))-0.08954626)*cos(x)),(x/x))-x)",
          "g": "(min(((tan(cos(min(0.5566991,0.85034895)))-x)*cos(0.58290607)),(0.7808082/0.13712347))-x)"
        }
      },
      {
        "fitness": 0,
        "expressions": {
          "r": "0.75338334",
          "b": "0.14754975",
          "g": "0.9852841"
        }
      },
      {
        "fitness": 0,
        "expressions": {
          "r": "y",
          "b": "y",
          "g": "x"
        }
      },
      {
        "fitness": 0,
        "expressions": {
          "r": "pow((x/(pow(var(sin(x)),y)+max(0.031960487,y))),0.56282794)",
          "b": "pow((x/(pow(var(sin(y)),y)+max(x,0.009570301))),y)",
          "g": "pow((y/(pow(var(sin(x)),0.8427619)+max(y,x))),x)"
        }
      },
      {
        "fitness": 0,
        "expressions": {
          "r": "0.6035793",
          "b": "y",
          "g": "x"
        }
      },
      {
        "fitness": 0,
        "expressions": {
          "r": "min(0.21720958,max(sin(pow(x,var(0.59199053))),y))",
          "b": "min(y,max(sin(pow(y,var(0.5667211))),y))",
          "g": "min(0.49489582,max(sin(pow(x,var(0.778494))),y))"
        }
      },
      {
        "fitness": 0,
        "expressions": {
          "r": "0.47681147",
          "b": "x",
          "g": "0.3605799"
        }
      },
      {
        "fitness": 0,
        "expressions": {
          "r": "y",
          "b": "0.7921584",
          "g": "y"
        }
      },
      {
        "fitness": 0,
        "expressions": {
          "r": "0.28781158",
          "b": "y",
          "g": "0.45986903"
        }
      },
      {
        "fitness": 0,
        "expressions": {
          "r": "pow(pow(min((y*tan(pow(tan(y),y))),(x-y)),y),y)",
          "b": "pow(pow(min((y*tan(pow(tan(0.84386533),x))),(0.5882476-x)),0.4902218),0.8777899)",
          "g": "pow(pow(min((y*tan(pow(tan(0.14893878),y))),(x-0.010923207)),x),0.417822)"
        }
      },
      {
        "fitness": 0,
        "expressions": {
          "r": "min((0.19143999/0.18928277),y)",
          "b": "min((y/x),y)",
          "g": "min((y/x),y)"
        }
      },
      {
        "fitness": 0,
        "expressions": {
          "r": "cos(max((cos(x)+x),(0.3312369/x)))",
          "b": "cos(max((cos(0.14518422)+y),(x/x)))",
          "g": "cos(max((cos(y)+x),(y/0.6874441)))"
        }
      },
      {
        "fitness": 0,
        "expressions": {
          "r": "0.9482027",
          "b": "0.04505092",
          "g": "0.12682468"
        }
      },
      {
        "fitness": 0,
        "expressions": {
          "r": "var(sin((y-y)))",
          "b": "var(sin((0.63605475-0.40983278)))",
          "g": "var(sin((x-y)))"
        }
      }
    ],
    "timestamp": "21h:54m:18s"
  }],
  "timestamp": "2024-05-05-21-54-12"
}