{
  "id": "xpuax42k-45y0-bdlu-pi2a-vji8krrgxr5i",
  "parameters": {
    "crossoverRate": 0.30000001192092896,
    "eliteSize": 2,
    "tournamentSize": 3,
    "mutationRate": 0.8999999761581421,
    "populationSize": 10
  },
  "populations": [
    {
      "generation": 0,
      "id": "4qrbyk1p-m9cc-ox7x-jmqx-jojaii8a1vk9",
      "individuals": [
        {
          "fitness": 0,
          "expressions": {
            "r": "x",
            "b": "0.33540952",
            "g": "x"
          }
        },
        {
          "fitness": 0,
          "expressions": {
            "r": "(pow(((x*y)+(min((auh(aul((y-x),x),0.7794843)-auh(((y*0.25891775)*min(0.8972817,y)),y)),aud(aul(tan(y),0.8631994),0.38558257))+x)),y)+x)",
            "b": "(pow(((0.13662189*0.3459245)+(min((auh(aul((y-0.2759562),y),y)-auh(((y*x)*min(x,x)),0.16995692)),aud(aul(tan(x),y),x))+x)),x)+x)",
            "g": "(pow(((y*0.41707277)+(min((auh(aul((x-0.31181824),x),0.0041080713)-auh(((0.1255812*y)*min(x,y)),x)),aud(aul(tan(0.2585383),0.45388895),x))+x)),x)+0.74518865)"
          }
        },
        {
          "fitness": 0,
          "expressions": {
            "r": "max(0.52476615,min(x,(tan(y)/min(((0.16342252/0.01937002)+sin(min(x,(sin(y)-(y-0.9617293))))),x))))",
            "b": "max(0.5408206,min(x,(tan(y)/min(((y/0.75325763)+sin(min(x,(sin(y)-(0.2948243-x))))),x))))",
            "g": "max(0.5873496,min(x,(tan(y)/min(((y/0.8699019)+sin(min(0.44018555,(sin(0.79627293)-(x-0.934006))))),0.40321362))))"
          }
        },
        {
          "fitness": 0,
          "expressions": {
            "r": "cos(auh(min(min(x,0.4343598),aud(cos(aud(min(cos(cos(x)),y),((0.5107566*x)-x))),aud(tan(max(x,auh(sin(y),y))),(x-y)))),var(tan(x))))",
            "b": "cos(auh(min(min(x,0.7835961),aud(cos(aud(min(cos(cos(0.31147993)),y),((x*y)-0.78635573))),aud(tan(max(y,auh(sin(x),x))),(x-x)))),var(tan(x))))",
            "g": "cos(auh(min(min(x,y),aud(cos(aud(min(cos(cos(0.84554243)),y),((x*y)-x))),aud(tan(max(0.3766653,auh(sin(x),y))),(y-x)))),var(tan(0.28588128))))"
          }
        },
        {
          "fitness": 0,
          "expressions": {
            "r": "pow(pow(max(auh(y,auh(sin(aul(max(max(0.8047512,y),tan(y)),x)),x)),tan(sin((var(x)/0.55923575)))),aul(((tan(max(0.3693552,auh((0.37643248*x),y)))-0.7877033)*x),y)),0.4769345)",
            "b": "pow(pow(max(auh(0.666103,auh(sin(aul(max(max(x,0.29067314),tan(0.49248326)),0.8691042)),0.6306923)),tan(sin((var(x)/y)))),aul(((tan(max(y,auh((y*y),0.900267)))-x)*y),0.99575794)),x)",
            "g": "pow(pow(max(auh(x,auh(sin(aul(max(max(x,x),tan(0.8809474)),0.5262113)),y)),tan(sin((var(0.79694474)/0.37413132)))),aul(((tan(max(x,auh((x*y),0.38848132)))-0.48738652)*x),x)),y)"
          }
        },
        {
          "fitness": 0,
          "expressions": {
            "r": "0.59327334",
            "b": "0.64346606",
            "g": "0.8469338"
          }
        },
        {
          "fitness": 0,
          "expressions": {
            "r": "y",
            "b": "y",
            "g": "0.9721173"
          }
        },
        {
          "fitness": 0,
          "expressions": {
            "r": "(pow(auh(cos(sin(sin(y))),0.17036676),0.14675993)-x)",
            "b": "(pow(auh(cos(sin(sin(0.106533945))),0.53218836),x)-0.15241814)",
            "g": "(pow(auh(cos(sin(sin(y))),x),0.32252812)-y)"
          }
        },
        {
          "fitness": 0,
          "expressions": {
            "r": "(y-var(y))",
            "b": "(0.37410057-var(x))",
            "g": "(x-var(x))"
          }
        },
        {
          "fitness": 0,
          "expressions": {
            "r": "aul(min(tan(aud(sin(auh(y,max(tan(0.4911663),(aul(x,0.82413876)-min(x,x))))),min(max(0.5352155,max(0.2510503,auh((0.42998672*y),y))),((x+tan((0.29657972*x)))*max(x,0.23598933))))),min(0.87171614,y)),0.9874318)",
            "b": "aul(min(tan(aud(sin(auh(y,max(tan(y),(aul(y,x)-min(x,y))))),min(max(x,max(x,auh((0.8629743*0.7123282),x))),((0.80334073+tan((y*y)))*max(y,y))))),min(0.7659788,x)),y)",
            "g": "aul(min(tan(aud(sin(auh(x,max(tan(0.65014994),(aul(0.47758985,0.72869056)-min(y,0.8445377))))),min(max(x,max(x,auh((x*0.5662093),x))),((x+tan((y*x)))*max(x,y))))),min(y,0.04343033)),0.91439563)"
          }
        },
        {
          "fitness": 0,
          "expressions": {
            "r": "0.9861653",
            "b": "x",
            "g": "y"
          }
        },
        {
          "fitness": 0,
          "expressions": {
            "r": "aul(0.30785626,0.65573037)",
            "b": "aul(x,y)",
            "g": "aul(0.11131257,x)"
          }
        },
        {
          "fitness": 0,
          "expressions": {
            "r": "y",
            "b": "y",
            "g": "x"
          }
        },
        {
          "fitness": 0,
          "expressions": {
            "r": "pow(0.6875063,(x-y))",
            "b": "pow(x,(y-0.19337243))",
            "g": "pow(0.38812655,(x-0.6347725))"
          }
        },
        {
          "fitness": 0,
          "expressions": {
            "r": "aud(((var(min(y,x))/pow((tan(tan(x))-auh(0.5209272,0.24249011)),0.19213629))/y),min((var(x)+x),min((cos((var(tan(aul(y,y)))*aul(pow(0.8080053,(y+x)),0.8596861)))/var((auh(0.13134402,tan((x-x)))+var((max(x,0.18030435)/0.27337343))))),0.19178116)))",
            "b": "aud(((var(min(x,y))/pow((tan(tan(0.925135))-auh(y,0.83132243)),0.20692545))/0.7931219),min((var(0.9170796)+y),min((cos((var(tan(aul(x,x)))*aul(pow(0.59956115,(y+y)),y)))/var((auh(0.99694437,tan((x-y)))+var((max(0.22686553,x)/0.23550385))))),0.10038328)))",
            "g": "aud(((var(min(x,0.9687311))/pow((tan(tan(y))-auh(y,y)),0.3167081))/0.7993142),min((var(0.7428825)+x),min((cos((var(tan(aul(y,0.41935086)))*aul(pow(x,(y+x)),x)))/var((auh(0.7396783,tan((0.34007174-y)))+var((max(0.7113862,x)/y))))),y)))"
          }
        },
        {
          "fitness": 0,
          "expressions": {
            "r": "tan(max((cos((y-x))+cos(0.8687507)),aud(0.5638318,x)))",
            "b": "tan(max((cos((y-0.14481854))+cos(x)),aud(0.9233483,0.15141678)))",
            "g": "tan(max((cos((0.51865125-0.114926934))+cos(x)),aud(y,0.826917)))"
          }
        },
        {
          "fitness": 0,
          "expressions": {
            "r": "min((var((auh(var(min(tan(var(y)),0.18276554)),y)/sin(x)))+0.11313969),y)",
            "b": "min((var((auh(var(min(tan(var(y)),0.3233655)),0.12936723)/sin(0.43347216)))+y),x)",
            "g": "min((var((auh(var(min(tan(var(y)),y)),x)/sin(y)))+y),y)"
          }
        },
        {
          "fitness": 0,
          "expressions": {
            "r": "cos(x)",
            "b": "cos(0.15668464)",
            "g": "cos(y)"
          }
        }
      ],
      "timestamp": "22h:25m:59s"
    },
    {
      "generation": 1,
      "ascendantID": "4qrbyk1p-m9cc-ox7x-jmqx-jojaii8a1vk9",
      "id": "lzes0l1r-im8i-ik0m-r6ye-kjnohnml3dir",
      "individuals": [
        {
          "fitness": 0,
          "expressions": {
            "r": "x",
            "b": "0.33540952",
            "g": "x"
          }
        },
        {
          "fitness": 0,
          "expressions": {
            "r": "(y-var((cos(x)-x)))",
            "b": "(0.37410057-var((cos(x)-x)))",
            "g": "(x-var((cos(y)-0.28629577)))"
          }
        },
        {
          "fitness": 0,
          "expressions": {
            "r": "y",
            "b": "y",
            "g": "0.9721173"
          }
        },
        {
          "fitness": 0,
          "expressions": {
            "r": "x",
            "b": "0.33540952",
            "g": "x"
          }
        },
        {
          "fitness": 0,
          "expressions": {
            "r": "aul(min(tan(aud(sin(auh(y,max(tan(0.4911663),(max(x,0.82413876)-max(x,x))))),min(min(0.5352155,max(0.2510503,aul(sin(0.42998672),y))),((x+tan((0.29657972*x)))*max(x,0.23598933))))),min(0.87171614,y)),0.9874318)",
            "b": "aul(min(tan(aud(sin(auh(y,max(tan(y),(max(y,x)-max(x,y))))),min(min(x,max(x,aul(sin(0.8629743),x))),((0.80334073+tan((y*y)))*max(y,y))))),min(0.7659788,x)),y)",
            "g": "aul(min(tan(aud(sin(auh(x,max(tan(0.65014994),(max(0.47758985,0.72869056)-max(y,0.8445377))))),min(min(x,max(x,aul(sin(x),x))),((x+tan((y*x)))*max(x,y))))),min(y,0.04343033)),0.91439563)"
          }
        },
        {
          "fitness": 0,
          "expressions": {
            "r": "pow(pow(max(auh(y,auh(sin(aul(max(max(0.8047512,y),tan(y)),x)),x)),tan(cos((var(x)/0.55923575)))),aul(((tan(max(0.3693552,auh((0.37643248*x),y)))-0.7877033)-x),y)),0.4769345)",
            "b": "pow(pow(max(auh(0.666103,auh(sin(aul(max(max(x,0.29067314),tan(0.49248326)),0.8691042)),0.6306923)),tan(cos((var(x)/y)))),aul(((tan(max(y,auh((y*y),0.900267)))-x)-y),0.99575794)),x)",
            "g": "pow(pow(max(auh(x,auh(sin(aul(max(max(x,x),tan(0.8809474)),0.6793113)),y)),tan(cos((var(0.79694474)/0.37413132)))),aul(((tan(max(x,auh((x*y),0.38848132)))-0.48738652)-x),x)),y)"
          }
        },
        {
          "fitness": 0,
          "expressions": {
            "r": "0.9861653",
            "b": "x",
            "g": "y"
          }
        },
        {
          "fitness": 0,
          "expressions": {
            "r": "x",
            "b": "0.33540952",
            "g": "x"
          }
        },
        {
          "fitness": 0,
          "expressions": {
            "r": "0.59327334",
            "b": "0.64346606",
            "g": "0.8469338"
          }
        },
        {
          "fitness": 0,
          "expressions": {
            "r": "0.9861653",
            "b": "x",
            "g": "y"
          }
        },
        {
          "fitness": 0,
          "expressions": {
            "r": "pow(pow(max(auh(y,auh(sin(aul(max(max(0.7004227,y),tan(y)),x)),x)),var(sin((var(x)/0.55923575)))),aud(((tan(min(0.3693552,auh((0.37643248*x),y)))-0.7877033)*x),y)),0.4769345)",
            "b": "pow(pow(max(auh(0.666103,auh(sin(aul(max(max(x,0.29067314),tan(0.49248326)),0.8691042)),0.6306923)),var(sin((var(x)/y)))),aud(((tan(min(y,auh((y*y),0.900267)))-x)*y),0.99575794)),x)",
            "g": "pow(pow(max(auh(x,auh(sin(aul(max(max(x,x),tan(0.8809474)),0.5262113)),y)),var(sin((var(0.79694474)/0.37413132)))),aud(((tan(min(x,auh((x*y),0.38848132)))-0.48738652)*x),x)),y)"
          }
        },
        {
          "fitness": 0,
          "expressions": {
            "r": "pow(pow(max(auh(y,auh(sin(aul(max(max(0.8047512,y),var(y)),x)),x)),var(sin((var(x)/0.55923575)))),aul(((tan(max(0.3693552,auh((0.37643248*x),y)))-0.7877033)-x),y)),0.4769345)",
            "b": "pow(pow(max(auh(0.666103,auh(sin(aul(max(max(x,0.29067314),var(0.49248326)),x)),0.6306923)),var(sin((var(x)/y)))),aul(((tan(max(y,auh((y*y),0.900267)))-x)-y),0.99575794)),x)",
            "g": "pow(pow(max(auh(x,auh(sin(aul(max(max(x,x),var(0.8809474)),0.5262113)),y)),var(sin((var(0.79694474)/0.37413132)))),aul(((tan(max(x,auh((x*y),0.38848132)))-0.48738652)-x),x)),y)"
          }
        },
        {
          "fitness": 0,
          "expressions": {
            "r": "0.59327334",
            "b": "0.64346606",
            "g": "0.8469338"
          }
        },
        {
          "fitness": 0,
          "expressions": {
            "r": "min(0.52476615,max(x,(tan(y)*min(((0.16342252/0.01937002)+sin(min(x,(cos(y)-(y+0.9617293))))),x))))",
            "b": "min(0.5408206,max(x,(tan(y)*min(((y/0.75325763)+sin(min(x,(cos(y)-(0.2948243+x))))),x))))",
            "g": "min(0.5873496,max(x,(tan(y)*min(((y/0.8699019)+sin(min(0.44018555,(cos(0.79627293)-(x+0.934006))))),0.40321362))))"
          }
        },
        {
          "fitness": 0,
          "expressions": {
            "r": "aud(((var(min(y,x))/pow((tan(tan(x))-auh(0.36431897,0.24249011)),0.19213629))/y),pow((var(x)+x),min((cos((var(var(aul(y,y)))*aul(pow(0.8080053,(y+x)),0.8596861)))/tan((auh(0.13134402,tan((x-x)))+var((max(x,0.18030435)/0.27337343))))),0.19178116)))",
            "b": "aud(((var(min(x,y))/pow((tan(tan(0.925135))-auh(y,0.83132243)),0.20692545))/0.7931219),pow((var(0.9170796)+y),min((cos((var(var(aul(x,x)))*aul(pow(0.59956115,(y+y)),y)))/tan((auh(0.99694437,tan((x-y)))+var((max(0.22686553,x)/0.23550385))))),0.10038328)))",
            "g": "aud(((var(min(x,0.9687311))/pow((tan(tan(y))-auh(y,y)),0.3167081))/0.7993142),pow((var(0.7428825)+x),min((cos((var(var(aul(y,0.41935086)))*aul(pow(x,(y+x)),x)))/tan((auh(0.7396783,tan((0.34007174-y)))+var((max(0.7113862,x)/y))))),y)))"
          }
        },
        {
          "fitness": 0,
          "expressions": {
            "r": "min((var(x)+0.11313969),y)",
            "b": "min((var(y)+y),x)",
            "g": "min((var(y)+y),y)"
          }
        },
        {
          "fitness": 0,
          "expressions": {
            "r": "pow(0.6875063,(x-y))",
            "b": "pow(x,(y-0.19337243))",
            "g": "pow(0.38812655,(x-0.6347725))"
          }
        },
        {
          "fitness": 0,
          "expressions": {
            "r": "aul(min(cos(aud(sin(auh(y,max(tan(0.4911663),(aul(x,0.82413876)*min(x,x))))),min(max(0.5352155,min(0.2510503,auh((0.42998672*y),y))),((x+tan((0.29657972*x)))*max(x,0.23598933))))),min(0.87171614,y)),0.9874318)",
            "b": "aul(min(cos(aud(sin(auh(y,max(tan(y),(aul(y,x)*min(x,y))))),min(max(x,min(x,auh((0.8629743*0.7123282),x))),((0.80334073+tan((y*y)))*max(y,y))))),min(0.7659788,x)),y)",
            "g": "aul(min(cos(aud(sin(auh(x,max(tan(0.65014994),(aul(0.47758985,0.72869056)*min(y,0.8445377))))),min(max(x,min(x,auh((x*0.5662093),x))),((x+tan((y*x)))*max(x,y))))),min(y,0.04343033)),0.91439563)"
          }
        }
      ],
      "timestamp": "22h:26m:6s"
    },
    {
      "generation": 2,
      "ascendantID": "lzes0l1r-im8i-ik0m-r6ye-kjnohnml3dir",
      "id": "cg1pd6u5-67rp-yeeq-vv04-1i676e25oxmy",
      "individuals": [
        {
          "fitness": 0,
          "expressions": {
            "r": "x",
            "b": "0.33540952",
            "g": "x"
          }
        },
        {
          "fitness": 0,
          "expressions": {
            "r": "0.59327334",
            "b": "0.64346606",
            "g": "0.8469338"
          }
        },
        {
          "fitness": 0,
          "expressions": {
            "r": "y",
            "b": "y",
            "g": "0.9721173"
          }
        },
        {
          "fitness": 0,
          "expressions": {
            "r": "pow(aul(x,x),(x-y))",
            "b": "pow(aul(x,0.23753268),(y-0.19337243))",
            "g": "pow(aul(x,y),(x-0.6347725))"
          }
        },
        {
          "fitness": 0,
          "expressions": {
            "r": "0.9861653",
            "b": "x",
            "g": "y"
          }
        },
        {
          "fitness": 0,
          "expressions": {
            "r": "0.59327334",
            "b": "0.64346606",
            "g": "0.8469338"
          }
        },
        {
          "fitness": 0,
          "expressions": {
            "r": "x",
            "b": "0.33540952",
            "g": "x"
          }
        },
        {
          "fitness": 0,
          "expressions": {
            "r": "0.9861653",
            "b": "x",
            "g": "y"
          }
        },
        {
          "fitness": 0,
          "expressions": {
            "r": "aul(pow(tan(aud(sin(auh(y,max(tan(0.4911663),(max(x,0.82413876)/max(x,x))))),min(min(0.5352155,max(0.2510503,aul(sin(0.42998672),y))),((x-tan((0.29657972*x)))*auh(x,0.23598933))))),pow(0.87171614,y)),0.9874318)",
            "b": "aul(pow(tan(aud(sin(auh(y,max(tan(y),(max(y,x)/max(x,y))))),min(min(x,max(x,aul(sin(0.8629743),x))),((0.80334073-tan((y*y)))*auh(y,y))))),pow(0.7659788,x)),y)",
            "g": "aul(pow(tan(aud(sin(auh(x,max(tan(0.65014994),(max(0.47758985,0.72869056)/max(y,0.8445377))))),min(min(x,max(x,aul(sin(x),x))),((x-tan((y*x)))*auh(x,y))))),pow(y,0.04343033)),0.91439563)"
          }
        },
        {
          "fitness": 0,
          "expressions": {
            "r": "pow(pow(max(auh(y,auh(sin(aul(max(auh(0.8047512,y),var(y)),x)),x)),aud(sin((var(x)/0.55923575)),y)),aul(((tan(max(0.3693552,auh((0.37643248*x),y)))-0.7877033)*x),y)),0.4769345)",
            "b": "pow(pow(max(auh(0.8158668,auh(sin(aul(max(auh(x,0.29067314),var(0.49248326)),x)),0.6306923)),aud(sin((var(x)/y)),y)),aul(((tan(max(y,auh((y*y),0.900267)))-x)*y),x)),x)",
            "g": "pow(pow(max(auh(x,auh(sin(aul(max(auh(x,x),var(0.8809474)),0.5262113)),y)),aud(sin((var(0.79694474)/0.37413132)),0.30890512)),aul(((tan(max(x,auh((x*y),0.38848132)))-0.48738652)*x),x)),y)"
          }
        },
        {
          "fitness": 0,
          "expressions": {
            "r": "x",
            "b": "0.33540952",
            "g": "x"
          }
        },
        {
          "fitness": 0,
          "expressions": {
            "r": "y",
            "b": "y",
            "g": "0.9721173"
          }
        },
        {
          "fitness": 0,
          "expressions": {
            "r": "pow(pow(max(auh(y,auh(sin(aul(max(max(0.8047512,y),var(y)),x)),x)),var(sin((var(x)/0.55923575)))),auh(((tan(max(0.33949876,auh((0.37643248*x),y)))-0.9451781)-x),y)),0.4769345)",
            "b": "pow(pow(max(auh(0.666103,auh(sin(aul(max(max(x,0.29067314),var(0.49248326)),0.63712174)),0.6306923)),var(sin((var(x)/y)))),auh(((tan(max(y,auh((y*y),0.900267)))-x)-y),0.99575794)),x)",
            "g": "pow(pow(max(auh(x,auh(sin(aul(max(max(x,x),var(0.8809474)),x)),y)),var(sin((var(0.79694474)/0.37413132)))),auh(((tan(max(x,auh((x*y),0.38848132)))-0.48738652)-x),x)),y)"
          }
        },
        {
          "fitness": 0,
          "expressions": {
            "r": "pow(pow(max(auh(y,auh(sin(auh(max(auh(0.7004227,y),tan(y)),x)),x)),var(sin((var(x)/0.55923575)))),aud(((tan(auh(0.3693552,auh((0.37643248*x),y)))+0.7877033)*x),y)),0.4769345)",
            "b": "pow(pow(max(auh(0.666103,auh(sin(auh(max(auh(x,0.29067314),tan(0.49248326)),0.8691042)),0.6306923)),var(sin((var(x)/y)))),aud(((tan(auh(y,auh((y*y),0.900267)))+x)*y),0.99575794)),x)",
            "g": "pow(pow(max(auh(x,auh(sin(auh(max(auh(x,x),tan(0.8809474)),0.5262113)),y)),var(sin((var(0.79694474)/0.37413132)))),aud(((tan(auh(x,auh((x*y),0.38848132)))+0.48738652)*x),x)),y)"
          }
        },
        {
          "fitness": 0,
          "expressions": {
            "r": "aud(((var(max(y,x))/pow(0.59327334,0.19213629))/y),pow((var(x)+x),min((cos((var(aud(aul(y,y),y))*aul(pow(0.8080053,(y+x)),0.8596861)))/tan((auh(0.13134402,tan((x-x)))+var((min(x,0.31702474)/0.27337343))))),0.19178116)))",
            "b": "aud(((var(max(x,y))/pow(0.64346606,0.20692545))/0.7931219),pow((var(x)+y),min((cos((var(aud(aul(x,x),0.25850344))*aul(pow(0.59956115,(y+y)),y)))/tan((auh(0.99694437,tan((x-y)))+var((min(0.22686553,x)/0.23550385))))),0.10038328)))",
            "g": "aud(((var(max(x,0.9687311))/pow(0.8469338,0.3167081))/0.7993142),pow((var(0.7428825)+x),min((cos((var(aud(aul(y,0.41935086),0.78196084))*aul(pow(x,(y+x)),x)))/tan((auh(0.7396783,tan((0.34007174-y)))+var((min(0.7113862,x)/y))))),y)))"
          }
        },
        {
          "fitness": 0,
          "expressions": {
            "r": "aul(min(cos(aud(sin(auh(y,max(tan(0.4911663),(aul(x,0.82413876)*min(x,x))))),min(max(0.40867525,min(0.2510503,auh((0.42998672*y),y))),((x+tan((0.29657972*x)))*max(x,0.23598933))))),min(0.87171614,y)),0.9874318)",
            "b": "aul(min(cos(aud(sin(auh(y,max(tan(y),(aul(y,x)*min(x,y))))),min(max(x,min(x,auh((0.8629743*0.7123282),x))),((0.80334073+tan((y*y)))*max(y,y))))),min(0.7659788,x)),y)",
            "g": "aul(min(cos(aud(sin(auh(x,max(tan(0.676451),(aul(0.47758985,0.72869056)*min(y,0.8445377))))),min(max(x,min(x,auh((x*0.5662093),x))),((x+tan((y*x)))*max(x,y))))),min(y,0.04343033)),0.91439563)"
          }
        },
        {
          "fitness": 0,
          "expressions": {
            "r": "aul(max(cos(aud(sin(auh(y,max(tan(0.4911663),(auh(x,0.82413876)*pow(x,x))))),min(max(0.5352155,min(0.2510503,auh((0.42998672*y),y))),((x+tan(x))*max(x,0.23598933))))),min(0.87171614,y)),0.9874318)",
            "b": "aul(max(cos(aud(sin(auh(y,max(tan(y),(auh(y,x)*pow(x,y))))),min(max(x,min(0.91998684,auh((0.8629743*0.7123282),x))),((0.80334073+tan(0.33540952))*max(y,y))))),min(0.7659788,x)),y)",
            "g": "aul(max(cos(aud(sin(auh(x,max(tan(0.65014994),(auh(0.47758985,0.72869056)*pow(y,0.8445377))))),min(max(x,min(x,auh((x*0.5662093),x))),((x+tan(x))*max(x,y))))),min(y,0.04343033)),0.91439563)"
          }
        },
        {
          "fitness": 0,
          "expressions": {
            "r": "pow(pow(max(auh(y,auh(sin(aul(max(max(0.8047512,y),tan(y)),x)),x)),tan(cos((tan(x)/0.55923575)))),aul(((tan(max(0.3693552,auh((0.37643248*x),y)))-0.7877033)-x),y)),0.4769345)",
            "b": "pow(pow(max(auh(0.666103,auh(sin(aul(max(max(x,0.29067314),tan(0.49248326)),0.8691042)),0.6306923)),tan(cos((tan(x)/y)))),aul(((tan(max(y,auh((y*y),0.900267)))-x)-y),0.99575794)),x)",
            "g": "pow(pow(max(auh(x,auh(sin(aul(max(max(x,x),tan(0.8809474)),0.6793113)),y)),tan(cos((tan(0.79694474)/0.37413132)))),aul(((tan(max(x,auh((x*y),0.38848132)))-0.48738652)-x),x)),y)"
          }
        }
      ],
      "timestamp": "22h:26m:7s"
    },
    {
      "generation": 3,
      "ascendantID": "cg1pd6u5-67rp-yeeq-vv04-1i676e25oxmy",
      "id": "d8lvic3q-6rio-0gnu-w1rl-wmt5noi0nd8m",
      "individuals": [
        {
          "fitness": 0,
          "expressions": {
            "r": "x",
            "b": "0.33540952",
            "g": "x"
          }
        },
        {
          "fitness": 0,
          "expressions": {
            "r": "pow(pow(max(auh(y,auh(sin(aul(max(auh(0.8047512,y),var(y)),x)),x)),aud(sin((var(x)*0.6970326)),y)),aul(((tan(max(0.30437052,auh((0.37643248*x),y)))-0.7877033)*x),y)),0.4769345)",
            "b": "pow(pow(max(auh(0.8158668,auh(sin(aul(max(auh(x,0.29067314),var(0.49248326)),x)),0.6306923)),aud(sin((var(x)*y)),y)),aul(((tan(max(y,auh((y*y),0.900267)))-x)*y),x)),x)",
            "g": "pow(pow(max(auh(x,auh(sin(aul(max(auh(x,x),var(0.8809474)),0.5262113)),y)),aud(sin((var(0.79694474)*0.37413132)),0.30890512)),aul(((tan(max(x,auh((x*y),0.38848132)))-0.48738652)*x),x)),y)"
          }
        },
        {
          "fitness": 0,
          "expressions": {
            "r": "aul(pow(var(aud(cos(auh(y,max(tan(0.4911663),(max(x,0.82413876)/max(x,x))))),min(min(0.5352155,max(0.2510503,aul(sin(0.42998672),y))),((x-cos((0.29657972*x)))*auh(x,0.23598933))))),pow(0.87171614,y)),0.9874318)",
            "b": "aul(pow(var(aud(cos(auh(y,max(tan(y),(max(y,x)/max(x,y))))),min(min(x,max(x,aul(sin(0.8629743),x))),((0.80334073-cos((y*y)))*auh(y,y))))),pow(0.7659788,x)),y)",
            "g": "aul(pow(var(aud(cos(auh(x,max(tan(0.65014994),(max(0.47758985,0.72869056)/max(y,0.8445377))))),min(min(x,max(x,aul(sin(x),x))),((x-cos((y*x)))*auh(x,y))))),pow(y,0.022443049)),0.91439563)"
          }
        },
        {
          "fitness": 0,
          "expressions": {
            "r": "0.9861653",
            "b": "x",
            "g": "y"
          }
        },
        {
          "fitness": 0,
          "expressions": {
            "r": "aul(pow(tan(aud(sin(auh(y,max(tan(0.4911663),sin(0.42998672)))),min(min(0.5352155,max(0.2510503,auh(sin(0.42998672),y))),((x+tan((0.29657972*x)))-auh(x,0.23598933))))),pow(0.87171614,y)),0.9874318)",
            "b": "aul(pow(tan(aud(sin(auh(y,max(tan(y),sin(0.8629743)))),min(min(x,max(x,auh(sin(0.8629743),x))),((0.80334073+tan((y*y)))-auh(y,y))))),pow(0.7659788,x)),y)",
            "g": "aul(pow(tan(aud(sin(auh(x,max(tan(0.65014994),sin(x)))),min(min(x,max(x,auh(sin(x),x))),((x+tan((y*x)))-auh(x,y))))),pow(y,0.04343033)),0.91439563)"
          }
        },
        {
          "fitness": 0,
          "expressions": {
            "r": "pow(aul(x,x),(x-y))",
            "b": "pow(aul(x,0.23753268),(y-0.19337243))",
            "g": "pow(aul(x,y),(x-0.6347725))"
          }
        },
        {
          "fitness": 0,
          "expressions": {
            "r": "0.9861653",
            "b": "x",
            "g": "y"
          }
        },
        {
          "fitness": 0,
          "expressions": {
            "r": "aud((min(x,0.7496547)/x),min((var(x)+x),min((cos((aud(var(aud(y,y)),x)*aul(pow(0.8080053,(y+x)),0.8596861)))/tan((auh(0.13134402,tan((x-x)))+var((min(x,0.31702474)/0.27337343))))),0.19178116)))",
            "b": "aud((min(x,x)/0.94341606),min((var(x)+y),min((cos((aud(var(aud(x,x)),x)*aul(pow(0.59956115,(y+y)),y)))/tan((auh(0.99694437,tan((x-y)))+var((min(0.22686553,x)/0.23550385))))),0.10038328)))",
            "g": "aud((min(y,0.69333655)/0.0066230893),min((var(0.7428825)+x),min((cos((aud(var(aud(y,0.41935086)),y)*aul(pow(x,(y+x)),x)))/tan((auh(0.7396783,tan((0.34007174-y)))+var((min(0.7113862,x)/y))))),y)))"
          }
        },
        {
          "fitness": 0,
          "expressions": {
            "r": "pow(pow(max(auh(y,auh(sin(aud(max(max(0.8047512,y),var(y)),x)),x)),var(sin((tan(x)/0.55923575)))),auh(((cos(max(0.50967103,auh((0.37643248*x),y)))-0.9451781)-x),y)),0.4769345)",
            "b": "pow(pow(max(auh(0.666103,auh(sin(aud(max(max(x,0.29067314),var(0.31630093)),0.63712174)),0.6306923)),var(sin((tan(x)/y)))),auh(((cos(max(y,auh((y*y),0.900267)))-x)-y),0.99575794)),x)",
            "g": "pow(pow(max(auh(x,auh(sin(aud(max(max(x,x),var(0.8809474)),x)),y)),var(sin((tan(0.79694474)/0.37413132)))),auh(((cos(max(0.8831978,auh((x*y),0.38848132)))-0.48738652)-x),x)),y)"
          }
        },
        {
          "fitness": 0,
          "expressions": {
            "r": "pow(pow(max(auh(y,auh(sin(auh(max(auh(0.7004227,y),tan(y)),x)),x)),var(cos((aud(x,y)/0.55923575)))),var(((tan(auh(0.3693552,auh((0.37643248*x),y)))+x)*x))),0.4769345)",
            "b": "pow(pow(max(auh(0.666103,auh(sin(auh(max(auh(x,0.29067314),tan(0.30253804)),0.8691042)),0.6306923)),var(cos((aud(x,x)/y)))),var(((tan(auh(y,auh((y*y),0.900267)))+x)*y))),x)",
            "g": "pow(pow(max(auh(x,auh(sin(auh(max(auh(x,x),tan(0.8809474)),0.5262113)),y)),var(cos((aud(0.79694474,y)/0.37413132)))),var(((tan(auh(x,auh((x*y),0.38848132)))+0.6654201)*x))),y)"
          }
        },
        {
          "fitness": 0,
          "expressions": {
            "r": "aul(pow(tan(aud(cos(auh(y,max(tan(0.4911663),(y*max(x,x))))),min(min(0.5352155,max(0.2510503,aul(sin(0.42998672),y))),((x-tan((0.29657972*x)))*auh(x,0.23598933))))),pow(0.87171614,x)),0.9874318)",
            "b": "aul(pow(tan(aud(cos(auh(y,max(tan(y),(0.905765*max(x,y))))),min(min(x,max(x,aul(sin(0.8629743),x))),((0.80334073-tan((y*y)))*auh(y,y))))),pow(0.7659788,x)),y)",
            "g": "aul(pow(tan(aud(cos(auh(x,max(tan(0.65014994),(y*max(y,0.8445377))))),min(min(x,max(x,aul(sin(x),x))),((x-tan((y*x)))*auh(x,y))))),pow(y,0.04343033)),0.91439563)"
          }
        },
        {
          "fitness": 0,
          "expressions": {
            "r": "pow(pow(auh(max(y,x),aud(sin((var(x)/0.55923575)),y)),aul(((tan(max(0.3693552,auh((0.37643248*x),y)))-0.7877033)-x),y)),0.4769345)",
            "b": "pow(pow(auh(max(0.8158668,0.33540952),aud(sin((var(x)/y)),y)),aul(((tan(max(y,auh((y*y),0.900267)))-x)-y),x)),x)",
            "g": "pow(pow(auh(max(x,x),aud(sin((var(0.79694474)/0.37413132)),0.30890512)),aul(((tan(max(x,auh((x*y),0.38848132)))-0.48738652)-x),x)),y)"
          }
        },
        {
          "fitness": 0,
          "expressions": {
            "r": "x",
            "b": "0.33540952",
            "g": "x"
          }
        },
        {
          "fitness": 0,
          "expressions": {
            "r": "0.59327334",
            "b": "0.64346606",
            "g": "0.8469338"
          }
        },
        {
          "fitness": 0,
          "expressions": {
            "r": "pow(aul(x,x),(x-y))",
            "b": "pow(aul(x,0.23753268),(y-0.19337243))",
            "g": "pow(aul(x,y),(x-0.6347725))"
          }
        },
        {
          "fitness": 0,
          "expressions": {
            "r": "aul(min(cos(aud(sin(max(y,auh(tan(0.4911663),(aul(x,0.82413876)*min(x,x))))),min(max(0.40867525,min(0.2510503,min((0.42998672*y),y))),((x+tan((0.29657972*x)))*min(x,0.23598933))))),min(x,y)),0.9874318)",
            "b": "aul(min(cos(aud(sin(max(y,auh(tan(y),(aul(y,x)*min(x,y))))),min(max(x,min(x,min((0.75124365*0.7123282),x))),((0.80334073+tan((y*y)))*min(y,y))))),min(0.7659788,x)),y)",
            "g": "aul(min(cos(aud(sin(max(x,auh(tan(0.676451),(aul(0.47758985,0.72869056)*min(y,0.8445377))))),min(max(x,min(x,min((x*0.5662093),0.7593254))),((x+tan((y*x)))*min(x,y))))),min(x,0.04343033)),0.91439563)"
          }
        },
        {
          "fitness": 0,
          "expressions": {
            "r": "y",
            "b": "y",
            "g": "0.9721173"
          }
        },
        {
          "fitness": 0,
          "expressions": {
            "r": "0.9861653",
            "b": "x",
            "g": "y"
          }
        }
      ],
      "timestamp": "22h:26m:10s"
    },
    {
      "generation": 4,
      "ascendantID": "d8lvic3q-6rio-0gnu-w1rl-wmt5noi0nd8m",
      "id": "2jhbg3ie-itet-94v8-n6sd-p6xvoihiwbsr",
      "individuals": [
        {
          "fitness": 0,
          "expressions": {
            "r": "x",
            "b": "0.33540952",
            "g": "x"
          }
        },
        {
          "fitness": 0,
          "expressions": {
            "r": "x",
            "b": "0.33540952",
            "g": "x"
          }
        },
        {
          "fitness": 0,
          "expressions": {
            "r": "aud((max(x,0.7496547)/x),min((var(x)+x),min((cos((aud(var(aud(y,y)),x)*aul(pow(0.8080053,(y+0.872622)),0.8596861)))/tan((auh(0.13134402,tan((x+x)))+var((max(x,0.31702474)/0.27337343))))),0.19178116)))",
            "b": "aud((max(x,x)/0.94341606),min((var(x)+y),min((cos((aud(var(aud(x,x)),x)*aul(pow(0.59956115,(y+y)),y)))/tan((auh(0.99694437,tan((x+y)))+var((max(0.22686553,x)/0.23550385))))),0.10038328)))",
            "g": "aud((max(y,0.69333655)/0.0066230893),min((var(0.7428825)+x),min((cos((aud(var(aud(y,0.41935086)),y)*aul(pow(x,(y+x)),x)))/tan((auh(0.7396783,tan((0.34007174+y)))+var((max(0.7113862,y)/y))))),y)))"
          }
        },
        {
          "fitness": 0,
          "expressions": {
            "r": "0.9861653",
            "b": "x",
            "g": "y"
          }
        },
        {
          "fitness": 0,
          "expressions": {
            "r": "aul(pow(0.9861653,min(0.87171614,y)),0.9874318)",
            "b": "aul(pow(x,min(0.7659788,x)),y)",
            "g": "aul(pow(y,min(y,0.022443049)),0.91439563)"
          }
        },
        {
          "fitness": 0,
          "expressions": {
            "r": "pow(aul(x,x),(x-y))",
            "b": "pow(aul(x,0.23753268),(y-0.19337243))",
            "g": "pow(aul(x,y),(x-0.6347725))"
          }
        },
        {
          "fitness": 0,
          "expressions": {
            "r": "pow(pow(max(auh(y,auh(sin(aud(max(max(0.8047512,y),var(y)),x)),x)),aud(sin((tan(x)/0.55923575)),y)),auh(((cos(max(0.50967103,auh((0.37643248*x),y)))-0.9451781)-x),y)),0.4769345)",
            "b": "pow(pow(max(auh(0.666103,auh(sin(aud(max(max(x,0.29067314),var(0.31630093)),0.63712174)),0.6306923)),aud(sin((tan(x)/y)),y)),auh(((cos(max(y,auh((y*y),0.900267)))-x)-y),0.99575794)),x)",
            "g": "pow(pow(max(auh(x,auh(sin(aud(max(max(x,x),var(0.8809474)),x)),y)),aud(sin((tan(0.79694474)/0.37413132)),0.406161)),auh(((cos(max(0.8831978,auh((x*y),0.38848132)))-0.48738652)-x),x)),y)"
          }
        },
        {
          "fitness": 0,
          "expressions": {
            "r": "x",
            "b": "0.33540952",
            "g": "x"
          }
        },
        {
          "fitness": 0,
          "expressions": {
            "r": "pow(aul(x,x),(x-y))",
            "b": "pow(aul(x,0.23753268),(y-0.19337243))",
            "g": "pow(aul(x,y),(x-0.6347725))"
          }
        },
        {
          "fitness": 0,
          "expressions": {
            "r": "min(pow(max(auh(y,aul(sin(aul(max(aul(0.8047512,y),var(y)),x)),x)),aud(sin((var(x)*0.6970326)),y)),auh(((tan(max(0.30437052,auh((0.37643248*x),y)))-0.7877033)*x),y)),0.4769345)",
            "b": "min(pow(max(auh(0.8158668,aul(sin(aul(max(aul(x,0.29067314),var(0.49248326)),x)),0.6306923)),aud(sin((var(x)*y)),y)),auh(((tan(max(y,auh((y*y),0.900267)))-x)*y),x)),x)",
            "g": "min(pow(max(auh(x,aul(sin(aul(max(aul(x,x),var(0.8809474)),0.5262113)),y)),aud(sin((var(0.79694474)*0.37413132)),0.30890512)),auh(((tan(max(x,auh((x*y),0.38848132)))-0.48738652)*x),x)),y)"
          }
        },
        {
          "fitness": 0,
          "expressions": {
            "r": "aud(pow(tan(aul(sin(auh(y,max(var(0.4911663),sin(0.42998672)))),0.6925351)),pow(0.87171614,y)),0.9698013)",
            "b": "aud(pow(tan(aul(sin(auh(y,max(var(y),sin(0.8629743)))),0.083320856)),pow(0.7659788,x)),y)",
            "g": "aud(pow(tan(aul(sin(auh(x,max(var(0.65014994),sin(x)))),y)),pow(y,0.04343033)),0.91439563)"
          }
        },
        {
          "fitness": 0,
          "expressions": {
            "r": "pow(pow(max(auh(y,auh(cos(aul(max(auh(0.8047512,y),var(y)),x)),x)),aud(sin((var(x)*0.6970326)),y)),aul(((tan(max(0.30437052,auh((0.37643248*x),y)))-0.7877033)*x),y)),0.4769345)",
            "b": "pow(pow(max(auh(0.8158668,auh(cos(aul(max(auh(x,0.29067314),var(0.49248326)),x)),0.6306923)),aud(sin((var(x)*y)),y)),aul(((tan(max(y,auh((y*y),0.900267)))-x)*y),x)),x)",
            "g": "pow(pow(max(auh(x,auh(cos(aul(max(auh(x,x),var(0.8809474)),0.5262113)),y)),aud(sin((var(0.79694474)*0.37413132)),0.30890512)),aul(((tan(max(x,auh((x*y),0.38848132)))-0.48738652)*x),x)),y)"
          }
        },
        {
          "fitness": 0,
          "expressions": {
            "r": "var((min(x,0.7496547)/x))",
            "b": "var((min(x,x)/0.94341606))",
            "g": "var((min(y,0.69333655)/0.0066230893))"
          }
        },
        {
          "fitness": 0,
          "expressions": {
            "r": "pow(pow(max(auh(y,max(sin(aul(max(max(0.8047512,y),var(y)),x)),x)),aud(sin((var(x)*0.6970326)),y)),aul(((var(min(0.30437052,auh((0.37643248*x),y)))-0.7877033)*x),y)),0.4769345)",
            "b": "pow(pow(max(auh(0.8158668,max(sin(aul(max(max(x,0.29067314),var(0.49248326)),x)),0.6306923)),aud(sin((var(x)*y)),y)),aul(((var(min(y,auh((y*y),0.900267)))-x)*y),x)),x)",
            "g": "pow(pow(max(auh(x,max(sin(aul(max(max(x,x),var(0.8809474)),0.5262113)),y)),aud(sin((var(0.79694474)*0.37413132)),0.30890512)),aul(((var(min(x,auh((x*y),0.38848132)))-0.48738652)*x),x)),y)"
          }
        },
        {
          "fitness": 0,
          "expressions": {
            "r": "aul((min(x,0.7496547)/x),min((var(x)+x),min((cos((aud(var(aud(y,y)),x)*aul(pow(0.8080053,(y+x)),0.8596861)))/tan((auh(0.13134402,tan((x-x)))+var((min(x,0.31702474)*0.27337343))))),0.19178116)))",
            "b": "aul((min(x,x)/0.94341606),min((var(x)+y),min((cos((aud(var(aud(x,x)),x)*aul(pow(0.59956115,(y+y)),y)))/tan((auh(0.99694437,tan((x-y)))+var((min(0.22686553,x)*0.23550385))))),0.10038328)))",
            "g": "aul((min(y,0.69333655)/0.0066230893),min((var(0.7428825)+x),min((cos((aud(var(aud(y,0.6097809)),y)*aul(pow(x,(y+x)),x)))/tan((auh(0.7396783,tan((0.34007174-y)))+var((min(0.7113862,x)*y))))),y)))"
          }
        },
        {
          "fitness": 0,
          "expressions": {
            "r": "aul(pow(var(aud(cos(auh(y,max(cos(0.4911663),(max(x,0.82413876)/pow(x,x))))),min(min(0.5352155,max(0.2510503,aul(sin(0.42998672),y))),((x-cos((0.36771476*x)))*aul(y,0.23598933))))),pow(0.87171614,y)),0.9874318)",
            "b": "aul(pow(var(aud(cos(auh(y,max(cos(y),(max(y,x)/pow(x,y))))),min(min(x,max(x,aul(sin(0.8629743),x))),((0.80334073-cos((y*y)))*aul(y,y))))),pow(0.7659788,x)),y)",
            "g": "aul(pow(var(aud(cos(auh(x,max(cos(0.65014994),(max(0.47758985,0.72869056)/pow(y,0.8445377))))),min(min(x,max(x,aul(sin(x),x))),((x-cos((y*x)))*aul(x,y))))),pow(y,0.022443049)),0.91439563)"
          }
        },
        {
          "fitness": 0,
          "expressions": {
            "r": "aud((min(x,0.7496547)/x),pow((var(x)+x),min((cos((aud(var(aud(y,y)),x)*aul(pow(x,y),0.8596861)))/tan((auh(0.13134402,tan((x-x)))+var((min(x,0.31702474)/0.27337343))))),0.19178116)))",
            "b": "aud((min(x,x)/0.94341606),pow((var(x)+y),min((cos((aud(var(aud(x,x)),x)*aul(pow(x,y),y)))/tan((auh(0.99694437,tan((x-y)))+var((min(0.22686553,x)/0.23550385))))),0.10038328)))",
            "g": "aud((min(y,0.69333655)/0.0066230893),pow((var(0.7428825)+x),min((cos((aud(var(aud(y,0.41935086)),y)*aul(pow(y,y),x)))/tan((auh(0.60709894,tan((0.34007174-y)))+var((min(0.7113862,x)/y))))),y)))"
          }
        },
        {
          "fitness": 0,
          "expressions": {
            "r": "aul(min(tan(aud(cos(auh(y,max(tan(0.4911663),(y*max(x,x))))),min(max(0.5345151,max(0.2510503,aul(sin(0.6843654),y))),((x-tan((0.29657972*x)))*aul(x,0.23598933))))),pow(0.87171614,x)),0.9874318)",
            "b": "aul(min(tan(aud(cos(auh(y,max(tan(y),(0.905765*max(x,y))))),min(max(x,max(x,aul(sin(0.8629743),x))),((0.80334073-tan((y*y)))*aul(y,y))))),pow(0.7659788,x)),y)",
            "g": "aul(min(tan(aud(cos(auh(x,max(tan(0.65014994),(y*max(y,0.8445377))))),min(max(x,max(x,aul(sin(x),x))),((x-tan((y*x)))*aul(x,y))))),pow(y,0.04343033)),0.91439563)"
          }
        }
      ],
      "timestamp": "22h:26m:15s"
    },
    {
      "generation": 5,
      "ascendantID": "2jhbg3ie-itet-94v8-n6sd-p6xvoihiwbsr",
      "id": "xpzpeftt-kqj2-lblk-dc26-y47xy1g70y21",
      "individuals": [
        {
          "fitness": 0,
          "expressions": {
            "r": "x",
            "b": "0.33540952",
            "g": "x"
          }
        },
        {
          "fitness": 0,
          "expressions": {
            "r": "min(pow(max(auh(y,auh(sin(0.9861653),x)),aul(sin((var(x)/0.6970326)),y)),auh(((var(max(0.30437052,auh((0.37643248*x),y)))-0.7877033)-x),y)),0.4769345)",
            "b": "min(pow(max(auh(0.8158668,auh(sin(x),0.6306923)),aul(sin((var(x)/y)),y)),auh(((var(max(y,auh((y*y),0.900267)))-x)-y),x)),x)",
            "g": "min(pow(max(auh(x,auh(sin(y),y)),aul(sin((var(0.79694474)/0.37413132)),0.30890512)),auh(((var(max(x,auh((x*y),0.38848132)))-0.48738652)-x),x)),y)"
          }
        },
        {
          "fitness": 0,
          "expressions": {
            "r": "x",
            "b": "0.33540952",
            "g": "x"
          }
        },
        {
          "fitness": 0,
          "expressions": {
            "r": "aul(min(tan(aud(cos(aud(y,max(tan(0.4911663),(y*max(x,x))))),min(max(0.5345151,max(0.2510503,aul(sin(0.6843654),y))),((x-tan((0.29657972*x)))-aul(x,0.23598933))))),max(0.87171614,x)),0.9874318)",
            "b": "aul(min(tan(aud(cos(aud(y,max(tan(y),(0.905765*max(x,y))))),min(max(x,max(x,aul(sin(0.8629743),x))),((0.80334073-tan((y*y)))-aul(y,y))))),max(0.7659788,x)),y)",
            "g": "aul(min(tan(aud(cos(aud(x,max(tan(0.65014994),(y*max(y,0.8445377))))),min(max(x,max(x,aul(sin(x),x))),((x-tan((y*x)))-aul(x,y))))),max(y,0.04343033)),0.91439563)"
          }
        },
        {
          "fitness": 0,
          "expressions": {
            "r": "x",
            "b": "0.33540952",
            "g": "x"
          }
        },
        {
          "fitness": 0,
          "expressions": {
            "r": "min(aul(x,x),(x-y))",
            "b": "min(aul(x,0.23753268),(y-0.19337243))",
            "g": "min(aul(x,y),(x-0.6347725))"
          }
        },
        {
          "fitness": 0,
          "expressions": {
            "r": "aud((auh(x,0.7496547)/x),pow((var(x)+x),min((cos((aud(var(auh(y,y)),x)*max(pow(x,y),0.8596861)))/tan((auh(0.13134402,tan((x-x)))+var((min(x,0.31702474)/0.27337343))))),0.19178116)))",
            "b": "aud((auh(x,x)/0.94341606),pow((var(x)+y),min((cos((aud(var(auh(x,x)),x)*max(pow(x,y),y)))/tan((auh(0.99694437,tan((x-y)))+var((min(0.22686553,x)/0.23550385))))),0.10038328)))",
            "g": "aud((auh(y,0.69333655)/0.0066230893),pow((var(0.7428825)+x),min((cos((aud(var(auh(y,0.41935086)),y)*max(pow(y,y),x)))/tan((auh(0.60709894,tan((0.34007174-y)))+var((min(0.7113862,x)/y))))),y)))"
          }
        },
        {
          "fitness": 0,
          "expressions": {
            "r": "0.9861653",
            "b": "x",
            "g": "y"
          }
        },
        {
          "fitness": 0,
          "expressions": {
            "r": "aud(pow(tan(aul(sin(auh(y,max(var(0.4911663),sin(0.42998672)))),0.6925351)),pow(0.87171614,y)),0.9698013)",
            "b": "aud(pow(tan(aul(sin(auh(y,max(var(y),sin(0.8629743)))),0.083320856)),pow(0.7659788,x)),y)",
            "g": "aud(pow(tan(aul(sin(auh(x,max(var(0.65014994),sin(x)))),y)),pow(y,0.04343033)),0.91439563)"
          }
        },
        {
          "fitness": 0,
          "expressions": {
            "r": "pow(pow(max(auh(y,auh(cos(aul(max(auh(0.8047512,y),var(y)),x)),x)),aud(sin(y),y)),aul(((tan(max(0.30437052,auh((0.37643248*x),y)))-0.7877033)*x),y)),0.4769345)",
            "b": "pow(pow(max(auh(0.8158668,auh(cos(aul(max(auh(x,0.29067314),var(0.49248326)),x)),0.6306923)),aud(sin(x),y)),aul(((tan(max(y,auh((y*y),0.900267)))-x)*y),x)),x)",
            "g": "pow(pow(max(auh(x,auh(cos(aul(max(auh(x,x),var(0.8809474)),0.5262113)),y)),aud(sin(0.022443049),0.30890512)),aul(((tan(max(x,auh((y*y),0.38848132)))-0.48738652)*x),x)),y)"
          }
        },
        {
          "fitness": 0,
          "expressions": {
            "r": "aul(pow(0.9861653,min(0.87171614,y)),0.9874318)",
            "b": "aul(pow(x,min(0.7659788,x)),y)",
            "g": "aul(pow(y,min(y,0.022443049)),0.91439563)"
          }
        },
        {
          "fitness": 0,
          "expressions": {
            "r": "aul(min(tan(var(cos(auh(y,max(tan(0.4911663),(y*max(x,x))))))),pow(0.87171614,x)),0.9874318)",
            "b": "aul(min(tan(var(cos(auh(y,max(tan(y),(0.905765*max(x,y))))))),pow(0.7659788,x)),y)",
            "g": "aul(min(tan(var(cos(auh(x,max(tan(0.65014994),(y*max(y,0.8445377))))))),pow(y,0.04343033)),0.91439563)"
          }
        },
        {
          "fitness": 0,
          "expressions": {
            "r": "x",
            "b": "0.33540952",
            "g": "x"
          }
        },
        {
          "fitness": 0,
          "expressions": {
            "r": "aud(pow(tan(aul(sin(auh(y,max(var(0.4911663),sin(0.42998672)))),0.85114)),pow(0.87171614,y)),0.9698013)",
            "b": "aud(pow(tan(aul(sin(auh(y,max(var(y),sin(0.8629743)))),0.083320856)),pow(0.7659788,x)),y)",
            "g": "aud(pow(tan(aul(sin(auh(x,max(var(0.65014994),sin(x)))),y)),pow(y,0.04343033)),0.91439563)"
          }
        },
        {
          "fitness": 0,
          "expressions": {
            "r": "x",
            "b": "0.33540952",
            "g": "x"
          }
        },
        {
          "fitness": 0,
          "expressions": {
            "r": "x",
            "b": "0.33540952",
            "g": "x"
          }
        },
        {
          "fitness": 0,
          "expressions": {
            "r": "aul((min(x,0.76172996)/x),min((var(x)+x),min((tan((aud(var(aud(y,y)),x)*aul(pow(0.8080053,(y+x)),0.8596861)))/var((auh(0.13134402,var((x-x)))+var((min(x,0.31702474)*0.27337343))))),0.19178116)))",
            "b": "aul((min(x,x)/0.94341606),min((var(x)+y),min((tan((aud(var(aud(x,x)),x)*aul(pow(0.59956115,(y+y)),y)))/var((auh(0.99694437,var((x-y)))+var((min(0.22686553,x)*0.23550385))))),0.10038328)))",
            "g": "aul((min(y,0.69333655)/0.0066230893),min((var(0.7428825)+x),min((tan((aud(var(aud(y,0.6097809)),y)*aul(pow(x,(y+x)),x)))/var((auh(0.7396783,var((0.34007174-y)))+var((min(0.7113862,x)*y))))),y)))"
          }
        },
        {
          "fitness": 0,
          "expressions": {
            "r": "aud(pow(tan(aul(sin(aul(y,max(var(0.4911663),sin(0.42998672)))),0.6925351)),pow(0.87171614,y)),0.9698013)",
            "b": "aud(pow(tan(aul(sin(aul(y,max(var(y),sin(0.8629743)))),0.29158172)),pow(0.7659788,y)),y)",
            "g": "aud(pow(tan(aul(sin(aul(x,max(var(0.65014994),sin(x)))),y)),pow(y,0.04343033)),0.91439563)"
          }
        }
      ],
      "timestamp": "22h:26m:20s"
    },
    {
      "generation": 6,
      "ascendantID": "xpzpeftt-kqj2-lblk-dc26-y47xy1g70y21",
      "id": "d1mlscdb-3jrt-8vch-5mzg-pvmrkj8mlzln",
      "individuals": [
        {
          "fitness": 0,
          "expressions": {
            "r": "x",
            "b": "0.33540952",
            "g": "x"
          }
        },
        {
          "fitness": 0,
          "expressions": {
            "r": "x",
            "b": "0.33540952",
            "g": "x"
          }
        },
        {
          "fitness": 0,
          "expressions": {
            "r": "x",
            "b": "0.22953409",
            "g": "x"
          }
        },
        {
          "fitness": 0,
          "expressions": {
            "r": "aul((min(x,0.76172996)/x),min((tan(x)+x),min(sin(tan((aud(var(aud(y,y)),x)-aul(pow(0.8080053,(y+x)),0.8596861)))),0.19178116)))",
            "b": "aul((min(x,x)/0.94341606),min((tan(x)+y),min(sin(tan((aud(var(aud(x,x)),x)-aul(pow(0.59956115,(y+y)),y)))),0.10038328)))",
            "g": "aul((min(y,0.69333655)/0.0066230893),min((tan(0.7428825)+x),min(sin(tan((aud(var(aud(y,0.6097809)),y)-aul(pow(x,(y+x)),x)))),y)))"
          }
        },
        {
          "fitness": 0,
          "expressions": {
            "r": "aud(pow(tan(auh(sin(auh(y,max(var(0.4911663),sin(0.42998672)))),0.6925351)),pow(0.87171614,y)),0.9698013)",
            "b": "aud(pow(tan(auh(sin(auh(y,max(var(y),sin(0.8629743)))),0.083320856)),pow(0.7659788,x)),y)",
            "g": "aud(pow(tan(auh(sin(auh(x,max(var(0.8547097),sin(x)))),y)),pow(y,0.04343033)),0.91439563)"
          }
        },
        {
          "fitness": 0,
          "expressions": {
            "r": "aul(min(tan(var(cos(auh(y,max(tan(0.4911663),(y*max(x,x))))))),pow(0.87171614,x)),0.9874318)",
            "b": "aul(min(tan(var(cos(auh(y,max(tan(y),(0.905765*max(x,y))))))),pow(0.7659788,x)),y)",
            "g": "aul(min(tan(var(cos(auh(x,max(tan(0.50518686),(y*max(y,0.8445377))))))),pow(y,0.04343033)),0.91439563)"
          }
        },
        {
          "fitness": 0,
          "expressions": {
            "r": "aul(min(tan(var(cos(auh(y,max(tan(0.4911663),(y-max(x,x))))))),pow(0.87171614,x)),0.9874318)",
            "b": "aul(min(tan(var(cos(auh(y,max(tan(y),(0.905765-max(x,y))))))),pow(0.7659788,x)),y)",
            "g": "aul(min(tan(var(cos(auh(x,max(tan(0.65014994),(y-max(y,0.8445377))))))),pow(y,0.04343033)),0.91439563)"
          }
        },
        {
          "fitness": 0,
          "expressions": {
            "r": "pow(pow(min(auh(y,auh(cos(aul(max(auh(0.8047512,y),aud(y,x)),x)),x)),aud(sin(y),y)),x),0.4769345)",
            "b": "pow(pow(min(auh(0.8158668,auh(cos(aul(max(auh(x,0.29067314),aud(0.49248326,y)),x)),0.6306923)),aud(sin(x),y)),y),x)",
            "g": "pow(pow(min(auh(x,auh(cos(aul(max(auh(x,x),aud(0.8809474,x)),0.5262113)),y)),aud(sin(0.022443049),0.30890512)),0.15959162),y)"
          }
        },
        {
          "fitness": 0,
          "expressions": {
            "r": "aud((max(x,0.7496547)/x),pow((var(x)+x),max((cos((aud(var(auh(y,y)),x)*max(pow(x,y),0.8596861)))/tan((auh(0.13134402,tan((x-x)))+var((min(x,0.31702474)/0.27337343))))),0.19178116)))",
            "b": "aud((max(x,x)/0.94341606),pow((var(x)+y),max((cos((aud(var(auh(x,x)),x)*max(pow(x,y),y)))/tan((auh(0.99694437,tan((x-y)))+var((min(0.22686553,x)/0.23550385))))),0.10038328)))",
            "g": "aud((max(y,0.69333655)/0.0066230893),pow((var(0.45831847)+x),max((cos((aud(var(auh(y,0.41935086)),y)*max(pow(y,y),x)))/tan((auh(0.60709894,tan((0.34007174-y)))+var((min(0.6755821,x)/y))))),y)))"
          }
        },
        {
          "fitness": 0,
          "expressions": {
            "r": "x",
            "b": "0.4570604",
            "g": "x"
          }
        },
        {
          "fitness": 0,
          "expressions": {
            "r": "aud(pow(tan(aul(sin(aul(y,max(var(0.4911663),(0.42998672/y)))),0.85114)),pow(0.87171614,y)),0.9698013)",
            "b": "aud(pow(tan(aul(sin(aul(y,max(var(y),(0.8629743/0.7123282)))),0.083320856)),pow(0.7659788,x)),y)",
            "g": "aud(pow(tan(aul(sin(aul(x,max(var(0.65014994),(x/0.5662093)))),y)),pow(x,0.04343033)),0.91439563)"
          }
        },
        {
          "fitness": 0,
          "expressions": {
            "r": "x",
            "b": "0.33540952",
            "g": "x"
          }
        },
        {
          "fitness": 0,
          "expressions": {
            "r": "min(aul(x,x),(x-y))",
            "b": "min(aul(x,0.23753268),(y-0.19337243))",
            "g": "min(aul(x,y),(x-0.6347725))"
          }
        },
        {
          "fitness": 0,
          "expressions": {
            "r": "pow(pow(auh(auh(y,auh(sin(0.9861653),x)),aul(sin((tan(x)/0.7332262)),y)),auh(((var(max(0.30437052,auh((0.37643248-x),x)))-0.7877033)-x),y)),0.4769345)",
            "b": "pow(pow(auh(auh(0.8158668,auh(sin(x),0.6306923)),aul(sin((tan(x)/y)),y)),auh(((var(max(y,auh((y-y),0.900267)))-x)-y),x)),x)",
            "g": "pow(pow(auh(auh(x,auh(sin(y),y)),aul(sin((tan(0.79694474)/0.37413132)),0.30890512)),auh(((var(max(x,auh((x-y),0.2156055)))-0.48738652)-x),x)),y)"
          }
        },
        {
          "fitness": 0,
          "expressions": {
            "r": "aud(pow(tan(aul(cos(auh(y,max(var(0.7552874),sin(0.42998672)))),0.85114)),min(0.87171614,y)),0.9698013)",
            "b": "aud(pow(tan(aul(cos(auh(y,max(var(y),sin(0.8629743)))),0.083320856)),min(0.7659788,x)),y)",
            "g": "aud(pow(tan(aul(cos(auh(x,max(var(0.65014994),sin(x)))),y)),min(y,0.04343033)),0.91439563)"
          }
        },
        {
          "fitness": 0,
          "expressions": {
            "r": "aul(min(tan(aud(tan(aud(y,max(tan(0.4911663),(y*max(x,x))))),min(min(0.5345151,max(0.2510503,aud(sin(0.6843654),x))),((x-tan((0.29657972*x)))-aul(y,0.23598933))))),max(0.87171614,x)),0.9874318)",
            "b": "aul(min(tan(aud(tan(aud(y,max(tan(y),(0.905765*max(x,y))))),min(min(x,max(x,aud(sin(0.8629743),x))),((0.80334073-tan((y*y)))-aul(y,y))))),max(0.7659788,x)),y)",
            "g": "aul(min(tan(aud(tan(aud(x,max(tan(0.65014994),(y*max(y,0.8445377))))),min(min(x,max(x,aud(sin(x),x))),((x-tan((y*x)))-aul(x,y))))),max(y,0.04343033)),0.91439563)"
          }
        },
        {
          "fitness": 0,
          "expressions": {
            "r": "x",
            "b": "0.2608716",
            "g": "x"
          }
        },
        {
          "fitness": 0,
          "expressions": {
            "r": "aul(min(tan(var(cos(auh(y,max(tan(0.40685493),(y*max(x,x))))))),pow(0.87171614,x)),0.9874318)",
            "b": "aul(min(tan(var(cos(auh(y,max(tan(y),(0.905765*max(x,y))))))),pow(0.7659788,x)),y)",
            "g": "aul(min(tan(var(cos(auh(x,max(tan(0.65014994),(y*max(y,0.8445377))))))),pow(y,0.04343033)),0.91439563)"
          }
        }
      ],
      "timestamp": "22h:26m:21s"
    },
    {
      "generation": 7,
      "ascendantID": "d1mlscdb-3jrt-8vch-5mzg-pvmrkj8mlzln",
      "id": "1ago0lzn-9x9c-l1jp-cvj0-hgl5fnfm31gn",
      "individuals": [
        {
          "fitness": 0,
          "expressions": {
            "r": "x",
            "b": "0.33540952",
            "g": "x"
          }
        },
        {
          "fitness": 0,
          "expressions": {
            "r": "x",
            "b": "0.33540952",
            "g": "x"
          }
        },
        {
          "fitness": 0,
          "expressions": {
            "r": "aul(min(tan(var(cos(max(y,max(tan(0.4911663),(y*max(x,x))))))),pow(0.87171614,x)),0.9874318)",
            "b": "aul(min(tan(var(cos(max(y,max(tan(y),(0.905765*max(x,y))))))),pow(0.7659788,x)),y)",
            "g": "aul(min(tan(var(cos(max(x,max(tan(0.50518686),(y*max(y,0.8445377))))))),pow(y,0.04343033)),0.91439563)"
          }
        },
        {
          "fitness": 0,
          "expressions": {
            "r": "x",
            "b": "0.33540952",
            "g": "x"
          }
        },
        {
          "fitness": 0,
          "expressions": {
            "r": "x",
            "b": "0.22953409",
            "g": "x"
          }
        },
        {
          "fitness": 0,
          "expressions": {
            "r": "x",
            "b": "0.4570604",
            "g": "x"
          }
        },
        {
          "fitness": 0,
          "expressions": {
            "r": "aul(max(sin(var(cos(auh(y,max(tan(0.4911663),(y*max(x,x))))))),pow(0.87171614,x)),0.9874318)",
            "b": "aul(max(sin(var(cos(auh(y,max(tan(y),(0.905765*max(x,y))))))),pow(0.7659788,x)),y)",
            "g": "aul(max(sin(var(cos(auh(x,max(tan(0.50518686),(y*max(y,0.8445377))))))),pow(y,0.04343033)),0.91439563)"
          }
        },
        {
          "fitness": 0,
          "expressions": {
            "r": "aud((max(x,0.7496547)/x),pow((var(x)+x),max(sin(cos((aud(var(aul(y,y)),x)*max(pow(x,y),0.8596861)))),0.19178116)))",
            "b": "aud((max(x,x)/x),pow((var(x)+y),max(sin(cos((aud(var(aul(x,x)),x)*max(pow(x,y),y)))),0.10038328)))",
            "g": "aud((max(y,0.69333655)/0.0066230893),pow((var(0.45831847)+x),max(sin(cos((aud(var(aul(y,0.41935086)),y)*max(pow(y,y),x)))),y)))"
          }
        },
        {
          "fitness": 0,
          "expressions": {
            "r": "aul(min(cos(var(tan(auh(y,max(tan(0.4911663),(y/max(x,x))))))),pow(0.87171614,x)),0.9874318)",
            "b": "aul(min(cos(var(tan(auh(y,max(tan(y),(0.905765/max(x,y))))))),pow(0.7659788,x)),y)",
            "g": "aul(min(cos(var(tan(auh(x,max(tan(0.50518686),(y/max(y,0.8445377))))))),pow(y,0.04343033)),0.91439563)"
          }
        },
        {
          "fitness": 0,
          "expressions": {
            "r": "x",
            "b": "0.2608716",
            "g": "x"
          }
        },
        {
          "fitness": 0,
          "expressions": {
            "r": "aud(pow(tan(aul(sin(aud(aud(x,y),tan(y))),0.85114)),pow(0.87171614,y)),0.9698013)",
            "b": "aud(pow(tan(aul(sin(aud(aud(x,y),tan(y))),0.083320856)),pow(0.7659788,x)),y)",
            "g": "aud(pow(tan(aul(sin(aud(aud(x,y),tan(y))),y)),pow(x,0.04343033)),0.91439563)"
          }
        },
        {
          "fitness": 0,
          "expressions": {
            "r": "aud(pow(tan(auh(cos(auh(y,max(var(0.7552874),sin(0.42998672)))),0.85114)),min(0.87171614,y)),0.9698013)",
            "b": "aud(pow(tan(auh(cos(auh(y,max(var(y),sin(0.8629743)))),0.083320856)),min(0.7659788,x)),y)",
            "g": "aud(pow(tan(auh(cos(auh(x,max(var(0.65014994),sin(x)))),y)),min(y,0.04343033)),0.91439563)"
          }
        },
        {
          "fitness": 0,
          "expressions": {
            "r": "x",
            "b": "0.2608716",
            "g": "x"
          }
        },
        {
          "fitness": 0,
          "expressions": {
            "r": "pow(pow(min(auh(y,aul(cos(aul(min(auh(0.8047512,y),aud(y,x)),x)),x)),aud(sin(y),y)),x),0.4769345)",
            "b": "pow(pow(min(auh(0.8158668,aul(cos(aul(min(auh(x,0.29067314),aud(0.49248326,y)),x)),0.6306923)),aud(sin(x),y)),y),x)",
            "g": "pow(pow(min(auh(x,aul(cos(aul(min(auh(x,x),aud(0.8809474,x)),0.5262113)),y)),aud(sin(0.022443049),0.30890512)),0.15959162),y)"
          }
        },
        {
          "fitness": 0,
          "expressions": {
            "r": "min(aul(x,x),(x+y))",
            "b": "min(aul(x,0.23753268),(y+0.19337243))",
            "g": "min(aul(x,y),(x+0.6347725))"
          }
        },
        {
          "fitness": 0,
          "expressions": {
            "r": "aud(min(tan(var(cos(auh(y,max(tan(0.4911663),(y*pow(x,x))))))),pow(0.87171614,x)),0.9874318)",
            "b": "aud(min(tan(var(cos(auh(y,max(tan(y),(0.905765*pow(x,y))))))),pow(0.7659788,x)),y)",
            "g": "aud(min(tan(var(cos(auh(x,max(tan(0.50518686),(y*pow(y,0.8445377))))))),pow(y,0.04343033)),0.91439563)"
          }
        },
        {
          "fitness": 0,
          "expressions": {
            "r": "x",
            "b": "0.22953409",
            "g": "x"
          }
        },
        {
          "fitness": 0,
          "expressions": {
            "r": "x",
            "b": "0.22953409",
            "g": "x"
          }
        }
      ],
      "timestamp": "22h:26m:24s"
    },
    {
      "generation": 8,
      "ascendantID": "1ago0lzn-9x9c-l1jp-cvj0-hgl5fnfm31gn",
      "id": "54p724gc-geer-t87d-uzhn-o2v86l186t6f",
      "individuals": [
        {
          "fitness": 0,
          "expressions": {
            "r": "x",
            "b": "0.33540952",
            "g": "x"
          }
        },
        {
          "fitness": 0,
          "expressions": {
            "r": "x",
            "b": "0.2608716",
            "g": "x"
          }
        },
        {
          "fitness": 0,
          "expressions": {
            "r": "aul(min(tan(var(cos(max(y,max(tan(0.4911663),(y*max(x,x))))))),pow(0.87171614,x)),0.9874318)",
            "b": "aul(min(tan(var(cos(max(y,max(tan(y),(0.905765*max(x,y))))))),pow(0.7659788,x)),y)",
            "g": "aul(min(tan(var(cos(max(x,max(tan(0.50518686),(y*max(y,0.8445377))))))),pow(y,0.04343033)),0.91439563)"
          }
        },
        {
          "fitness": 0,
          "expressions": {
            "r": "aul(min(sin(var(tan(auh(y,x)))),pow(0.87171614,x)),0.9874318)",
            "b": "aul(min(sin(var(tan(auh(y,0.2608716)))),pow(0.7659788,x)),y)",
            "g": "aul(min(sin(var(tan(auh(x,x)))),pow(y,0.04343033)),0.91439563)"
          }
        },
        {
          "fitness": 0,
          "expressions": {
            "r": "aud(pow(cos(auh(cos(auh(y,max(var(0.7552874),sin(0.42998672)))),0.85114)),min(0.87171614,y)),0.9698013)",
            "b": "aud(pow(cos(auh(cos(auh(y,max(var(y),sin(0.8629743)))),0.083320856)),min(0.7659788,x)),y)",
            "g": "aud(pow(cos(auh(cos(auh(x,max(var(0.65014994),sin(x)))),y)),min(y,0.04343033)),0.91439563)"
          }
        },
        {
          "fitness": 0,
          "expressions": {
            "r": "x",
            "b": "0.33540952",
            "g": "x"
          }
        },
        {
          "fitness": 0,
          "expressions": {
            "r": "x",
            "b": "0.22953409",
            "g": "x"
          }
        },
        {
          "fitness": 0,
          "expressions": {
            "r": "aul(auh(sin(var(tan(aul(y,max(tan(0.4911663),(y*max(x,x))))))),pow(0.87171614,x)),0.9874318)",
            "b": "aul(auh(sin(var(tan(aul(y,max(tan(y),(0.905765*max(x,y))))))),pow(0.7659788,x)),y)",
            "g": "aul(auh(sin(var(tan(aul(x,max(tan(0.50518686),(y*max(y,0.8445377))))))),pow(y,0.04343033)),0.91439563)"
          }
        },
        {
          "fitness": 0,
          "expressions": {
            "r": "aud(0.1111114,0.9698013)",
            "b": "aud(y,y)",
            "g": "aud(x,0.91439563)"
          }
        },
        {
          "fitness": 0,
          "expressions": {
            "r": "x",
            "b": "0.33540952",
            "g": "x"
          }
        },
        {
          "fitness": 0,
          "expressions": {
            "r": "aul(min((var(cos(auh(y,max(cos(0.4911663),(y*max(x,x))))))/x),pow(0.87171614,x)),0.9874318)",
            "b": "aul(min((var(cos(auh(y,max(cos(y),(0.905765*max(x,y))))))/0.66607225),pow(0.7659788,x)),y)",
            "g": "aul(min((var(cos(auh(x,max(cos(0.50518686),(y*max(y,0.8445377))))))/x),pow(y,0.04343033)),0.91439563)"
          }
        },
        {
          "fitness": 0,
          "expressions": {
            "r": "x",
            "b": "0.33540952",
            "g": "x"
          }
        },
        {
          "fitness": 0,
          "expressions": {
            "r": "x",
            "b": "0.22953409",
            "g": "x"
          }
        },
        {
          "fitness": 0,
          "expressions": {
            "r": "aud(pow(tan(aul(sin(aud(aud(x,y),tan(y))),0.85114)),pow(0.87171614,y)),0.9698013)",
            "b": "aud(pow(tan(aul(sin(aud(aud(x,y),tan(y))),0.083320856)),pow(0.7659788,x)),y)",
            "g": "aud(pow(tan(aul(sin(aud(aud(x,y),tan(y))),y)),pow(x,0.04343033)),0.82802224)"
          }
        },
        {
          "fitness": 0,
          "expressions": {
            "r": "aul(max(sin(var(cos(auh(y,max(tan(0.4911663),(y*max(x,x))))))),pow(0.87171614,x)),0.9874318)",
            "b": "aul(max(sin(var(cos(auh(y,max(tan(y),(0.905765*max(x,y))))))),pow(0.7659788,x)),y)",
            "g": "aul(max(sin(var(cos(auh(x,max(tan(0.50518686),(y*max(y,0.8445377))))))),pow(y,0.04343033)),0.91439563)"
          }
        },
        {
          "fitness": 0,
          "expressions": {
            "r": "aud(min(cos(var(cos(auh(y,max(tan(0.4911663),(y-pow(x,x))))))),pow(0.87171614,x)),0.9874318)",
            "b": "aud(min(cos(var(cos(auh(y,max(tan(y),(0.905765-pow(x,y))))))),pow(0.7659788,x)),y)",
            "g": "aud(min(cos(var(cos(auh(x,max(tan(0.50518686),(y-pow(y,0.8445377))))))),pow(y,0.04343033)),0.91439563)"
          }
        },
        {
          "fitness": 0,
          "expressions": {
            "r": "min(aul(x,x),(x+y))",
            "b": "min(aul(x,0.23753268),(y+0.19337243))",
            "g": "min(aul(x,y),(x+0.6347725))"
          }
        },
        {
          "fitness": 0,
          "expressions": {
            "r": "aud(pow(tan(auh(cos(auh(y,max(var(0.7552874),(0.42998672/y)))),0.85114)),min(0.87171614,y)),0.9698013)",
            "b": "aud(pow(tan(auh(cos(auh(y,max(var(y),(0.8629743/0.7123282)))),0.083320856)),min(0.7659788,x)),y)",
            "g": "aud(pow(tan(auh(cos(auh(x,max(var(0.65014994),(x/0.5662093)))),y)),min(y,0.04343033)),0.91439563)"
          }
        }
      ],
      "timestamp": "22h:26m:27s"
    },
    {
      "generation": 9,
      "ascendantID": "54p724gc-geer-t87d-uzhn-o2v86l186t6f",
      "id": "updbc3jo-x7c0-8r99-abis-32ykgtukznj9",
      "individuals": [
        {
          "fitness": 0,
          "expressions": {
            "r": "x",
            "b": "0.33540952",
            "g": "x"
          }
        },
        {
          "fitness": 0,
          "expressions": {
            "r": "var(0.1111114)",
            "b": "var(y)",
            "g": "var(x)"
          }
        },
        {
          "fitness": 0,
          "expressions": {
            "r": "x",
            "b": "0.16344056",
            "g": "x"
          }
        },
        {
          "fitness": 0,
          "expressions": {
            "r": "aul(auh(sin(var(cos(aul(y,min(tan(0.4911663),(y*max(x,x))))))),pow(0.87171614,x)),0.9874318)",
            "b": "aul(auh(sin(var(cos(aul(y,min(tan(y),(0.905765*max(x,y))))))),pow(0.7659788,x)),y)",
            "g": "aul(auh(sin(var(cos(aul(x,min(tan(0.50518686),(y*max(y,0.8445377))))))),pow(y,0.04343033)),0.91439563)"
          }
        },
        {
          "fitness": 0,
          "expressions": {
            "r": "x",
            "b": "0.2608716",
            "g": "x"
          }
        },
        {
          "fitness": 0,
          "expressions": {
            "r": "x",
            "b": "0.33540952",
            "g": "x"
          }
        },
        {
          "fitness": 0,
          "expressions": {
            "r": "auh(auh(sin(var(tan(aul(y,max(tan(0.4911663),(y*min(x,x))))))),pow(0.87171614,x)),0.9874318)",
            "b": "auh(auh(sin(var(tan(aul(y,max(tan(y),(0.905765*min(x,y))))))),pow(0.7659788,x)),y)",
            "g": "auh(auh(sin(var(tan(aul(x,max(tan(0.50518686),(y*min(y,0.70898336))))))),pow(y,0.0)),0.91439563)"
          }
        },
        {
          "fitness": 0,
          "expressions": {
            "r": "x",
            "b": "0.33540952",
            "g": "x"
          }
        },
        {
          "fitness": 0,
          "expressions": {
            "r": "aud(pow(tan(aul(sin(aud(aud(x,y),tan(y))),0.85114)),pow(0.87171614,y)),0.9698013)",
            "b": "aud(pow(tan(aul(sin(aud(aud(x,y),tan(y))),0.083320856)),pow(0.7659788,x)),y)",
            "g": "aud(pow(tan(aul(sin(aud(aud(x,y),tan(y))),y)),pow(x,0.04343033)),0.82802224)"
          }
        },
        {
          "fitness": 0,
          "expressions": {
            "r": "var(min(cos(var(cos(auh(y,max(tan(0.4911663),(y/pow(x,x))))))),pow(0.87171614,x)))",
            "b": "var(min(cos(var(cos(auh(y,max(tan(y),(0.905765/pow(x,y))))))),pow(0.7659788,x)))",
            "g": "var(min(cos(var(cos(auh(x,max(tan(0.50518686),(y/pow(y,0.8445377))))))),pow(y,0.04343033)))"
          }
        },
        {
          "fitness": 0,
          "expressions": {
            "r": "x",
            "b": "0.33540952",
            "g": "x"
          }
        },
        {
          "fitness": 0,
          "expressions": {
            "r": "aud(pow(tan(auh(cos(auh(y,max(aud(0.7552874,0.8764692),(0.42998672/y)))),0.85114)),min(0.87171614,y)),0.9698013)",
            "b": "aud(pow(tan(auh(cos(auh(y,max(aud(y,y),(0.8629743/0.7123282)))),0.38250446)),min(0.7659788,x)),y)",
            "g": "aud(pow(tan(auh(cos(auh(x,max(aud(0.65014994,y),(x/0.5662093)))),y)),min(y,0.04343033)),0.91439563)"
          }
        },
        {
          "fitness": 0,
          "expressions": {
            "r": "aul(min((var(cos(auh(y,max(tan(0.4911663),(y*max(x,x))))))/x),pow(0.87171614,x)),0.9874318)",
            "b": "aul(min((var(cos(auh(y,max(tan(y),(0.905765*max(x,y))))))/0.66607225),pow(0.7659788,x)),y)",
            "g": "aul(min((var(cos(auh(x,max(tan(0.50518686),(y*max(y,0.8445377))))))/x),pow(y,0.04343033)),0.91439563)"
          }
        },
        {
          "fitness": 0,
          "expressions": {
            "r": "aud(pow(tan(sin(cos(x))),pow(0.87171614,y)),0.9698013)",
            "b": "aud(pow(tan(sin(cos(x))),pow(0.7659788,x)),y)",
            "g": "aud(pow(tan(sin(cos(y))),pow(x,0.04343033)),0.82802224)"
          }
        },
        {
          "fitness": 0,
          "expressions": {
            "r": "x",
            "b": "0.33540952",
            "g": "x"
          }
        },
        {
          "fitness": 0,
          "expressions": {
            "r": "x",
            "b": "0.33540952",
            "g": "x"
          }
        },
        {
          "fitness": 0,
          "expressions": {
            "r": "min(aul(x,x),(x+y))",
            "b": "min(aul(x,0.23753268),(y+0.19337243))",
            "g": "min(aul(x,y),(x+0.6347725))"
          }
        },
        {
          "fitness": 0,
          "expressions": {
            "r": "aud(pow(tan(auh(cos(auh(y,max(aud(0.7552874,0.93786144),(0.42998672*y)))),0.85114)),min(0.87171614,y)),0.9698013)",
            "b": "aud(pow(tan(auh(cos(auh(y,max(aud(y,y),(0.8629743*0.7123282)))),0.083320856)),min(0.7659788,x)),y)",
            "g": "aud(pow(tan(auh(cos(auh(x,max(aud(0.65014994,y),(x*0.5662093)))),y)),min(y,0.087306015)),0.91439563)"
          }
        }
      ],
      "timestamp": "22h:26m:28s"
    },
    {
      "generation": 10,
      "ascendantID": "updbc3jo-x7c0-8r99-abis-32ykgtukznj9",
      "id": "i0pb9f4v-kf87-h0my-kpdi-5v6opemoivj5",
      "individuals": [
        {
          "fitness": 0,
          "expressions": {
            "r": "x",
            "b": "0.33540952",
            "g": "x"
          }
        },
        {
          "fitness": 0,
          "expressions": {
            "r": "var(0.1111114)",
            "b": "var(y)",
            "g": "var(x)"
          }
        },
        {
          "fitness": 0,
          "expressions": {
            "r": "aud(pow(tan(auh(cos(aul(y,max(aud(0.7552874,0.93786144),(0.42998672*y)))),0.85114)),min(0.87171614,y)),0.9698013)",
            "b": "aud(pow(tan(auh(cos(aul(y,max(aud(y,y),(0.8629743*0.7123282)))),0.083320856)),min(0.7659788,x)),y)",
            "g": "aud(pow(tan(auh(cos(aul(x,max(aud(0.65014994,y),(x*0.5662093)))),y)),min(y,0.087306015)),0.91439563)"
          }
        },
        {
          "fitness": 0,
          "expressions": {
            "r": "aul(pow((var(cos(auh(y,max(tan(0.4911663),(y*max(x,x))))))/x),pow(0.87171614,x)),0.9874318)",
            "b": "aul(pow((var(cos(auh(y,max(tan(y),(0.905765*max(x,y))))))/0.66607225),pow(0.7659788,x)),y)",
            "g": "aul(pow((var(cos(auh(x,max(tan(0.50518686),(y*max(y,0.8445377))))))/x),pow(y,0.08198201)),0.91677815)"
          }
        },
        {
          "fitness": 0,
          "expressions": {
            "r": "aul(auh(sin(var(cos(aul(y,min(tan(0.4911663),(y*max(x,x))))))),pow(0.87171614,x)),0.9874318)",
            "b": "aul(auh(sin(var(cos(aul(y,min(tan(y),(0.905765*max(x,y))))))),pow(0.7659788,x)),y)",
            "g": "aul(auh(sin(var(cos(aul(x,min(tan(0.50518686),(y*max(y,0.8445377))))))),pow(y,0.04343033)),0.91439563)"
          }
        },
        {
          "fitness": 0,
          "expressions": {
            "r": "auh(auh(cos(var(tan(aud(y,max(tan(0.4911663),(y*min(x,x))))))),pow(0.87171614,x)),0.9874318)",
            "b": "auh(auh(cos(var(tan(aud(y,max(tan(y),(0.905765*min(x,y))))))),pow(0.7659788,x)),y)",
            "g": "auh(auh(cos(var(tan(aud(x,max(tan(0.50518686),(y*min(y,0.70898336))))))),pow(y,0.0)),0.91439563)"
          }
        },
        {
          "fitness": 0,
          "expressions": {
            "r": "x",
            "b": "0.33540952",
            "g": "x"
          }
        },
        {
          "fitness": 0,
          "expressions": {
            "r": "max(auh(sin(var(cos(aul(y,min(tan(0.4911663),(y*max(x,x))))))),pow(0.87171614,x)),0.9874318)",
            "b": "max(auh(sin(var(cos(aul(y,min(tan(y),(0.905765*max(x,y))))))),pow(0.7659788,x)),y)",
            "g": "max(auh(sin(var(cos(aul(x,min(tan(0.50518686),(y*max(y,0.8445377))))))),pow(y,0.04343033)),x)"
          }
        },
        {
          "fitness": 0,
          "expressions": {
            "r": "x",
            "b": "0.33540952",
            "g": "x"
          }
        },
        {
          "fitness": 0,
          "expressions": {
            "r": "aud(pow(tan(auh(cos(auh(y,max(aud(0.7552874,0.93786144),(0.42998672*y)))),0.85114)),min(0.87171614,y)),0.77716005)",
            "b": "aud(pow(tan(auh(cos(auh(y,max(aud(y,y),(0.8629743*0.7123282)))),0.083320856)),min(0.7659788,x)),y)",
            "g": "aud(pow(tan(auh(cos(auh(x,max(aud(0.65014994,y),(x*0.5662093)))),y)),min(y,0.087306015)),0.91439563)"
          }
        },
        {
          "fitness": 0,
          "expressions": {
            "r": "aul(min((var(cos(auh(y,min(tan(0.4911663),(y*max(x,x))))))/x),pow(0.87171614,x)),0.9874318)",
            "b": "aul(min((var(cos(auh(y,min(tan(y),(0.905765*max(x,y))))))/0.66607225),pow(0.7659788,x)),y)",
            "g": "aul(min((var(cos(auh(x,min(tan(0.50518686),(y*max(y,0.8445377))))))/x),pow(y,0.04343033)),0.89649355)"
          }
        },
        {
          "fitness": 0,
          "expressions": {
            "r": "x",
            "b": "0.16344056",
            "g": "x"
          }
        },
        {
          "fitness": 0,
          "expressions": {
            "r": "x",
            "b": "0.33540952",
            "g": "x"
          }
        },
        {
          "fitness": 0,
          "expressions": {
            "r": "x",
            "b": "0.33540952",
            "g": "x"
          }
        },
        {
          "fitness": 0,
          "expressions": {
            "r": "aud(pow(tan(auh(cos(auh(y,max(aud(0.7552874,0.93786144),(0.42998672*y)))),0.85114)),min(0.87171614,y)),0.9698013)",
            "b": "aud(pow(tan(auh(cos(auh(y,max(aud(y,y),(0.8629743*0.7123282)))),0.083320856)),min(0.7659788,x)),y)",
            "g": "aud(pow(tan(auh(cos(auh(x,max(aud(0.65014994,y),(x*0.5662093)))),y)),min(y,0.087306015)),0.91439563)"
          }
        },
        {
          "fitness": 0,
          "expressions": {
            "r": "var(min(var(var(cos(auh(y,max(tan(0.4911663),(y/pow(x,x))))))),pow(0.87171614,x)))",
            "b": "var(min(var(var(cos(auh(y,max(tan(y),(0.905765/pow(x,y))))))),pow(0.7659788,x)))",
            "g": "var(min(var(var(cos(auh(x,max(tan(0.50518686),(y/pow(y,0.8445377))))))),pow(y,0.04343033)))"
          }
        },
        {
          "fitness": 0,
          "expressions": {
            "r": "x",
            "b": "0.2608716",
            "g": "x"
          }
        },
        {
          "fitness": 0,
          "expressions": {
            "r": "aul(pow(tan(aul(sin(aud(aud(x,y),tan(y))),0.85114)),x),0.9698013)",
            "b": "aul(pow(tan(aul(sin(aud(aud(x,y),tan(y))),0.083320856)),0.33540952),y)",
            "g": "aul(pow(tan(aul(sin(aud(aud(x,y),tan(y))),y)),x),0.82802224)"
          }
        }
      ],
      "timestamp": "22h:26m:30s"
    },
    {
      "generation": 11,
      "ascendantID": "i0pb9f4v-kf87-h0my-kpdi-5v6opemoivj5",
      "id": "e0r8kl9i-j5ex-t2u5-io9h-n3vsm6xyclrj",
      "individuals": [
        {
          "fitness": 0,
          "expressions": {
            "r": "x",
            "b": "0.33540952",
            "g": "x"
          }
        },
        {
          "fitness": 0,
          "expressions": {
            "r": "aul(auh(sin(var(cos(aul(y,min(tan(0.4911663),(y*max(x,x))))))),pow(0.87171614,x)),0.9874318)",
            "b": "aul(auh(sin(var(cos(aul(y,min(tan(y),(0.905765*max(x,y))))))),pow(0.7659788,x)),y)",
            "g": "aul(auh(sin(var(cos(aul(x,min(tan(0.50518686),(y*max(y,0.8445377))))))),pow(y,0.04343033)),0.91439563)"
          }
        },
        {
          "fitness": 0,
          "expressions": {
            "r": "x",
            "b": "0.33540952",
            "g": "x"
          }
        },
        {
          "fitness": 0,
          "expressions": {
            "r": "x",
            "b": "0.16344056",
            "g": "x"
          }
        },
        {
          "fitness": 0,
          "expressions": {
            "r": "auh(min((var(cos(auh(y,max(tan(0.4911663),(pow(tan(aul(sin(aud(aud(x,y),tan(y))),0.85114)),x)*max(x,x))))))/x),pow(0.7185489,x)),0.9874318)",
            "b": "auh(min((var(cos(auh(y,max(tan(y),(pow(tan(aul(sin(aud(aud(x,y),tan(y))),0.083320856)),0.33540952)*max(x,y))))))/0.66607225),pow(0.7659788,x)),y)",
            "g": "auh(min((var(cos(auh(x,max(tan(0.50518686),(pow(tan(aul(sin(aud(aud(x,y),tan(y))),y)),x)*max(y,0.8445377))))))/x),pow(y,0.04343033)),0.89649355)"
          }
        },
        {
          "fitness": 0,
          "expressions": {
            "r": "aul(max(sin(var(tan(aul(y,max(tan(0.4911663),(y*max(x,x))))))),pow(0.87171614,x)),0.9874318)",
            "b": "aul(max(sin(var(tan(aul(y,max(tan(y),(0.905765*max(x,y))))))),pow(0.7659788,x)),y)",
            "g": "aul(max(sin(var(tan(aul(x,max(tan(0.50518686),(y*max(y,0.8445377))))))),pow(y,0.04343033)),0.91439563)"
          }
        },
        {
          "fitness": 0,
          "expressions": {
            "r": "aul(auh(cos(var(var(aud(y,max(tan(0.4911663),(y/min(x,x))))))),pow(0.87171614,x)),0.9874318)",
            "b": "aul(auh(cos(var(var(aud(y,max(tan(y),(0.905765/min(x,y))))))),pow(0.7659788,x)),y)",
            "g": "aul(auh(cos(var(var(aud(x,max(tan(0.50518686),(y/min(y,0.70898336))))))),pow(y,0.0)),0.91439563)"
          }
        },
        {
          "fitness": 0,
          "expressions": {
            "r": "auh(auh(cos(var(tan(aul(y,max(tan(0.4911663),(y*min(x,x))))))),pow(0.87171614,x)),0.9874318)",
            "b": "auh(auh(cos(var(tan(aul(y,max(tan(y),(0.905765*min(x,y))))))),pow(0.67702377,y)),y)",
            "g": "auh(auh(cos(var(tan(aul(x,max(tan(0.50518686),(y*min(y,0.70898336))))))),pow(y,0.0)),0.91439563)"
          }
        },
        {
          "fitness": 0,
          "expressions": {
            "r": "x",
            "b": "0.33540952",
            "g": "x"
          }
        },
        {
          "fitness": 0,
          "expressions": {
            "r": "aul(pow(tan(auh(sin(aud(aud(x,y),tan(y))),0.85114)),(((x+x)/min((((sin((aud(0.19860363,0.23415971)/aud(y,0.25964534)))*(pow(cos(0.5670097),auh(x,y))/0.9245426))/var((((y-y)/var(0.80926895))/(max(y,x)/(y-y)))))-tan(auh(aul(0.4619254,0.9427196),aul(min((y-x),y),var(max(y,0.05835861)))))),y))-max(tan(min(var(0.20925486),cos(0.9213921))),(0.19843447-y)))),0.9698013)",
            "b": "aul(pow(tan(auh(sin(aud(aud(x,y),tan(y))),0.083320856)),(((0.5661514+y)/min((((sin((aud(0.37999696,x)/aud(y,0.51126856)))*(pow(cos(0.87187976),auh(y,x))/y))/var((((y-0.38636094)/var(x))/(max(x,x)/(y-0.7263742)))))-tan(auh(aul(y,x),aul(min((x-0.7926144),y),var(max(y,x)))))),0.4870872))-max(tan(min(var(x),cos(x))),(y-y)))),y)",
            "g": "aul(pow(tan(auh(sin(aud(aud(x,y),tan(y))),y)),(((y+y)/min((((sin((aud(y,0.37396574)/aud(y,0.6050241)))*(pow(cos(y),auh(y,y))/x))/var((((y-y)/var(y))/(max(y,y)/(x-x)))))-tan(auh(aul(0.31145328,0.32582206),aul(min((0.9873923-0.36791664),y),var(max(x,x)))))),y))-max(tan(min(var(x),cos(x))),(x-0.6319524)))),0.82802224)"
          }
        },
        {
          "fitness": 0,
          "expressions": {
            "r": "x",
            "b": "0.28390175",
            "g": "x"
          }
        },
        {
          "fitness": 0,
          "expressions": {
            "r": "x",
            "b": "0.33540952",
            "g": "x"
          }
        },
        {
          "fitness": 0,
          "expressions": {
            "r": "x",
            "b": "0.16344056",
            "g": "x"
          }
        },
        {
          "fitness": 0,
          "expressions": {
            "r": "aul(pow((var(cos(auh(y,max(tan(0.4911663),(y*max(x,x))))))/x),pow(min(sin(min(aud(0.6460903,x),y)),0.78380764),x)),0.9874318)",
            "b": "aul(pow((var(cos(auh(y,max(tan(y),(0.905765*max(x,y))))))/0.66607225),pow(min(sin(min(aud(x,0.074871),y)),y),x)),y)",
            "g": "aul(pow((var(cos(auh(x,max(tan(0.50518686),(y*max(y,0.8445377))))))/x),pow(min(sin(min(aud(y,y),0.011579812)),0.25407618),0.11909095)),0.91677815)"
          }
        },
        {
          "fitness": 0,
          "expressions": {
            "r": "x",
            "b": "0.2608716",
            "g": "x"
          }
        },
        {
          "fitness": 0,
          "expressions": {
            "r": "var(min(var(var(cos(aul(y,max(tan(0.4911663),(y/pow(x,x))))))),pow(0.87171614,x)))",
            "b": "var(min(var(var(cos(aul(y,max(tan(y),(0.905765/pow(x,y))))))),pow(0.7659788,x)))",
            "g": "var(min(var(var(cos(aul(x,max(tan(0.50518686),(y/pow(y,0.8445377))))))),pow(y,0.04343033)))"
          }
        },
        {
          "fitness": 0,
          "expressions": {
            "r": "aud(pow(tan(auh(cos(auh(y,max(aud(0.7552874,0.93786144),(0.42998672-y)))),0.85114)),min(0.87171614,y)),0.77716005)",
            "b": "aud(pow(tan(auh(cos(auh(y,max(aud(y,y),(0.8629743-0.7123282)))),0.083320856)),min(0.7659788,x)),y)",
            "g": "aud(pow(tan(auh(cos(auh(x,max(aud(0.65014994,y),(x-0.5662093)))),y)),min(y,0.087306015)),0.91439563)"
          }
        },
        {
          "fitness": 0,
          "expressions": {
            "r": "x",
            "b": "0.2608716",
            "g": "x"
          }
        }
      ],
      "timestamp": "22h:26m:31s"
    },
    {
      "generation": 12,
      "ascendantID": "e0r8kl9i-j5ex-t2u5-io9h-n3vsm6xyclrj",
      "id": "x5x2vpk0-ucvp-plyk-4i7v-ex7b5vd363vg",
      "individuals": [
        {
          "fitness": 0,
          "expressions": {
            "r": "x",
            "b": "0.33540952",
            "g": "x"
          }
        },
        {
          "fitness": 0,
          "expressions": {
            "r": "auh(min((var(cos(auh(y,max(tan(0.4911663),(pow(cos(aud(sin(aud(x,tan(y))),0.85114)),x)*max(x,x))))))/x),pow(0.7185489,x)),0.9874318)",
            "b": "auh(min((var(cos(auh(y,max(tan(y),(pow(cos(aud(sin(aud(0.2608716,tan(y))),0.083320856)),0.33540952)*max(x,y))))))/0.66607225),pow(0.7659788,x)),y)",
            "g": "auh(min((var(cos(auh(x,max(tan(0.50518686),(pow(cos(aud(sin(aud(x,tan(y))),y)),x)*max(y,0.8445377))))))/x),pow(y,0.04343033)),0.89649355)"
          }
        },
        {
          "fitness": 0,
          "expressions": {
            "r": "aud(pow(tan(auh(cos(aul(y,max(aud(0.7552874,0.93786144),(0.42998672-y)))),0.85114)),pow(0.87171614,y)),0.77716005)",
            "b": "aud(pow(tan(auh(cos(aul(y,max(aud(y,y),(0.8629743-0.7123282)))),0.083320856)),pow(0.7659788,x)),y)",
            "g": "aud(pow(tan(auh(cos(aul(x,max(aud(0.65014994,y),(x-0.5662093)))),y)),pow(y,0.087306015)),0.91439563)"
          }
        },
        {
          "fitness": 0,
          "expressions": {
            "r": "x",
            "b": "0.33540952",
            "g": "0.9450719"
          }
        },
        {
          "fitness": 0,
          "expressions": {
            "r": "x",
            "b": "0.28390175",
            "g": "x"
          }
        },
        {
          "fitness": 0,
          "expressions": {
            "r": "aul(pow((var(cos(auh(y,max(tan(0.4911663),(y*max(x,x))))))/x),pow(min(sin(min(aud(0.6460903,x),y)),0.78380764),x)),0.9874318)",
            "b": "aul(pow((var(cos(auh(y,max(tan(y),(0.905765*max(x,y))))))/0.66607225),pow(min(sin(min(aud(x,0.074871),y)),y),x)),y)",
            "g": "aul(pow((var(cos(auh(x,max(tan(0.50518686),(y*max(y,0.8445377))))))/x),pow(min(sin(min(aud(y,y),0.011579812)),0.25407618),0.11909095)),0.91677815)"
          }
        },
        {
          "fitness": 0,
          "expressions": {
            "r": "x",
            "b": "0.28390175",
            "g": "x"
          }
        },
        {
          "fitness": 0,
          "expressions": {
            "r": "x",
            "b": "0.16344056",
            "g": "x"
          }
        },
        {
          "fitness": 0,
          "expressions": {
            "r": "x",
            "b": "0.2608716",
            "g": "x"
          }
        },
        {
          "fitness": 0,
          "expressions": {
            "r": "x",
            "b": "0.33540952",
            "g": "x"
          }
        },
        {
          "fitness": 0,
          "expressions": {
            "r": "x",
            "b": "0.33540952",
            "g": "x"
          }
        },
        {
          "fitness": 0,
          "expressions": {
            "r": "x",
            "b": "0.16344056",
            "g": "x"
          }
        },
        {
          "fitness": 0,
          "expressions": {
            "r": "var(min(var(var(cos(aul(y,max(tan(0.30081698),(y/pow(x,x))))))),pow(x,x)))",
            "b": "var(min(var(var(cos(aul(y,max(tan(y),(0.905765/pow(x,y))))))),pow(x,x)))",
            "g": "var(min(var(var(cos(aul(x,max(tan(0.50518686),(y/pow(y,0.8445377))))))),pow(0.0,0.04343033)))"
          }
        },
        {
          "fitness": 0,
          "expressions": {
            "r": "x",
            "b": "0.16344056",
            "g": "x"
          }
        },
        {
          "fitness": 0,
          "expressions": {
            "r": "aul(auh(sin(var(cos(aul(y,min(tan(0.4911663),(y*max(x,x))))))),pow(0.87171614,x)),0.9874318)",
            "b": "aul(auh(sin(var(cos(aul(y,min(tan(y),(0.905765*max(x,y))))))),pow(0.7659788,x)),y)",
            "g": "aul(auh(sin(var(cos(aul(x,min(tan(0.50518686),(y*max(y,0.8445377))))))),pow(y,0.04343033)),0.91439563)"
          }
        },
        {
          "fitness": 0,
          "expressions": {
            "r": "auh(min((var(cos(auh(y,max(tan(0.4911663),(pow(tan(aul(sin(aul(aud(x,y),tan(y))),0.85114)),x)*max(x,x))))))/x),pow(0.7185489,x)),0.9874318)",
            "b": "auh(min((var(cos(auh(y,max(tan(y),(pow(tan(aul(sin(aul(aud(x,y),tan(y))),0.083320856)),0.6169739)*max(x,y))))))/0.66607225),pow(0.7659788,x)),y)",
            "g": "auh(min((var(cos(auh(x,max(tan(0.50518686),(pow(tan(aul(sin(aul(aud(x,y),tan(y))),y)),x)*max(y,0.8445377))))))/x),pow(y,0.27245632)),0.89649355)"
          }
        },
        {
          "fitness": 0,
          "expressions": {
            "r": "x",
            "b": "0.33540952",
            "g": "x"
          }
        },
        {
          "fitness": 0,
          "expressions": {
            "r": "aul(max(sin(var(tan(aul(y,max(tan(0.4911663),(y*max(x,x))))))),pow(x,x)),0.9874318)",
            "b": "aul(max(sin(var(tan(aul(y,max(tan(y),(0.905765*max(x,y))))))),pow(0.47340286,x)),y)",
            "g": "aul(max(sin(var(tan(aul(x,max(tan(0.50518686),(y*max(y,0.8445377))))))),pow(x,0.0)),0.91439563)"
          }
        }
      ],
      "timestamp": "22h:26m:33s"
    },
    {
      "generation": 13,
      "ascendantID": "x5x2vpk0-ucvp-plyk-4i7v-ex7b5vd363vg",
      "id": "r8kjkfy1-dpo1-qh1p-xi7j-mvkp0zgkl6b7",
      "individuals": [
        {
          "fitness": 0,
          "expressions": {
            "r": "x",
            "b": "0.33540952",
            "g": "x"
          }
        },
        {
          "fitness": 0,
          "expressions": {
            "r": "x",
            "b": "0.33540952",
            "g": "x"
          }
        },
        {
          "fitness": 0,
          "expressions": {
            "r": "x",
            "b": "0.33540952",
            "g": "x"
          }
        },
        {
          "fitness": 0,
          "expressions": {
            "r": "x",
            "b": "0.33540952",
            "g": "x"
          }
        },
        {
          "fitness": 0,
          "expressions": {
            "r": "x",
            "b": "0.33540952",
            "g": "x"
          }
        },
        {
          "fitness": 0,
          "expressions": {
            "r": "aul(min(sin(var(cos(auh(y,min(tan(0.4911663),x))))),pow(0.7185489,x)),0.9874318)",
            "b": "aul(min(sin(var(cos(auh(y,min(tan(y),0.37334955))))),pow(0.7659788,x)),y)",
            "g": "aul(min(sin(var(cos(auh(x,min(tan(0.50518686),x))))),pow(y,0.04343033)),0.89649355)"
          }
        },
        {
          "fitness": 0,
          "expressions": {
            "r": "x",
            "b": "0.16344056",
            "g": "x"
          }
        },
        {
          "fitness": 0,
          "expressions": {
            "r": "x",
            "b": "0.16344056",
            "g": "x"
          }
        },
        {
          "fitness": 0,
          "expressions": {
            "r": "x",
            "b": "0.16344056",
            "g": "x"
          }
        },
        {
          "fitness": 0,
          "expressions": {
            "r": "x",
            "b": "0.16189794",
            "g": "x"
          }
        },
        {
          "fitness": 0,
          "expressions": {
            "r": "x",
            "b": "0.2608716",
            "g": "x"
          }
        },
        {
          "fitness": 0,
          "expressions": {
            "r": "x",
            "b": "0.33540952",
            "g": "x"
          }
        },
        {
          "fitness": 0,
          "expressions": {
            "r": "x",
            "b": "0.33540952",
            "g": "0.9450719"
          }
        },
        {
          "fitness": 0,
          "expressions": {
            "r": "x",
            "b": "0.33540952",
            "g": "x"
          }
        },
        {
          "fitness": 0,
          "expressions": {
            "r": "x",
            "b": "0.16344056",
            "g": "x"
          }
        },
        {
          "fitness": 0,
          "expressions": {
            "r": "x",
            "b": "0.33540952",
            "g": "0.9450719"
          }
        },
        {
          "fitness": 0,
          "expressions": {
            "r": "x",
            "b": "0.28390175",
            "g": "x"
          }
        },
        {
          "fitness": 0,
          "expressions": {
            "r": "x",
            "b": "0.33540952",
            "g": "x"
          }
        }
      ],
      "timestamp": "22h:26m:34s"
    }
  ],
  "timestamp": "2024-05-05-22-25-53"
}